Workbook

Sheet Read Me
A1: EF Client Hub Codebook
A2: Compiled for | B2: Executive Frame Client Hub (clients.executiveframe.co.nz), from the Charlotte Price Consulting Psychometric Codebook
A3: Compiled | B3: 18 October 2026 (duplicated from the CPC codebook compiled 26 September 2026)
A4: Scope | B4: The working set of 20 instruments selected for practice use, across 6 domains. 307 items are reproduced verbatim.
A5: Sources | B5: NovoPsych assessment pages and blank form PDFs, the official University of New South Wales DASS site, instrument developers, and original validation papers or authoritative open reproductions. Every record carries its source URL.
A7: Domains
A8: 1. Executive functioning and ADHD | B8: ESQ-R, CFI and ASRS. The ESQ-R is the executive skills core of both executive function batteries and the ASRS adds current adult ADHD symptom screening. The CFI measures cognitive flexibility and is now used in the Perfectionism battery rather than the executive function batteries.
A9: 2. Strengths knowledge, use and support at work | B9: SKS, SUS and SSES: whether a client knows their strengths, uses them, and is confident applying them. These are the measures that show change across a coaching engagement.
A10: 3. Adjacent occupational and wellbeing | B10: Core Self Evaluations Scale and Psychological Empowerment Scale: general positive self appraisal and felt empowerment in a work role.
A11: 4. Psychological distress screening | B11: DASS-21: depression, anxiety and stress over the past week. A screening measure used to establish whether coaching can safely proceed and whether clinical input is needed.
A12: 5. Repetitive negative thinking and self talk | B12: PTQ and RRS measure the process of repetitive negative thinking rather than the resulting mood, which the DASS-21 captures. FSCRS and PCI measure self critical and perfectionistic self talk, and the SCS-SF measures the self compassionate counterpart that coaching aims to build.
A13: 6. Motivation, self determination and goal pursuit | B13: Basic Psychological Need Satisfaction and Frustration Scale, Pure and Irrational Procrastination Scales, General Self-Efficacy Scale, Goal Commitment Scale and Goal Adjustment Scale. The last 2 are specific to goals: commitment to a goal the client names, and the capacity to let go of unattainable goals and take up new ones.
A15: Sheet | B15: Contents
A16: Hub Library | B16: One row per instrument as it appears in the Client Hub: the id and client facing name, whether it is included, its licence status for the hub (only cleared instruments can be assigned to clients), whether clients see strengths and areas of focus, item flags for Sarah, and the instructions shown on screen. Edit this sheet, then run npm run codebook to rebuild the hub library files.
A17: Hub Subscales | B17: One row per subscale as the hub scores it: client facing label, scoring direction, method, optional band thresholds (blank means thirds of the response range), the strength and focus wording clients see once released, and the Learning Hub topic each area of focus links to. All wording is draft for Sarah to approve.
A18: Batteries | B18: The 11 assessment forms used in practice, each a combination of instruments: which instruments each contains, total items, the matching report skill, what it assesses and its scoring cautions. Below it, a map showing which batteries use each instrument.
A19: Tally Prompt | B19: The prompt used to convert an existing Tally assessment form to a different battery, with instructions on which codebook fields to paste in and a checklist for testing the finished form.
A20: Instrument Summary | B20: One row per instrument with domain, availability, item counts, construct, respondent, cost and access, coaching application, instructions, response options, scoring, interpretation, cut-offs, norms, psychometrics, developer citation, copyright and source.
... A24: Individual instrument tabs | B24: One tab per instrument with its metadata block above its own item table.
A26: Hub conventions
A27: Licence status | B27: cleared: can be assigned to clients. review: in the library file but not uploadable until the licence is confirmed. permission: written permission needed before use. excluded: left out of the hub. The hub refuses to assign anything that is not cleared.
A28: Scoring direction | B28: difficulty: a higher score means more difficulty, so low scores are strengths and high scores are areas of focus. positive: the reverse. none: scored for Sarah only, never summarised to the client. Reverse scored items are reversed as min plus max minus the answer, so 1 to 7 scales reverse correctly.
A29: Conventions
A30: Verbatim wording | B30: Item text is transcribed word for word from the source named against each instrument. Nothing has been paraphrased or reconstructed. Where an item could not be retrieved the cell says so.
A31: Not stated on source | B31: The field is not published in the sources consulted.
A32: Reverse and filler | B32: TRUE in the reverse column means the item is reversed before summing. TRUE in the filler column means the item is not scored at all.
A33: Spelling | B33: Item wording is reproduced exactly as published, including United States spelling. Surrounding commentary uses UK spelling.
A35: Cautions and known gaps
B36: ESQ-R and CFI are scored in opposite directions: higher ESQ-R means more executive difficulty, higher CFI means more flexibility. The ESQ-R norms are 327 Malaysian working adults; the CFI norms are 196 university students.
B37: ASRS Part A of 14 or more is a positive screen, not a diagnosis. Gallup style caution applies: always pair with clinical interview, and with the WURS-25 where childhood history is needed.
B38: SKS and SUS items are taken from an open access peer reviewed reproduction (Frontiers in Psychology, 2023). CAPP asserts copyright over the scales and one later reuse redacted them, so they are viewable and freely reprinted rather than formally public domain.
B39: DASS-21 is a screening measure only. It describes the past week, contains no item on suicidal thinking and does not assess risk. Items 10, 17 and 21 are followed up directly when endorsed at 2 or 3, as the practice report builder does. Severity labels are population position descriptors, not diagnostic thresholds.
B40: No normative percentile tables exist for the SKS, SUS, SSES, CSES or PES. They are continuous measures best read against a client’s own baseline across repeated administration.
B41: RRS: only the 5 item Brooding and 5 item Reflection subscales are recommended for coaching use. The remaining 12 items overlap with depressive symptom content and are retained for completeness only. NovoPsych hosts the RRS, but its scoring and norm text could not be retrieved, so interpretation here rests on Treynor, Gonzalez and Nolen-Hoeksema (2003).
B42: FSCRS item 9 sits close to self harm content. Frame it with care, and treat endorsement as a prompt for a conversation rather than a score. The FSCRS carries an author copyright notice with no commercial grant or restriction stated; a short email to the authors settles its use in paid practice.
B43: SCS-SF: items 1, 4, 8, 9, 11 and 12 are reverse scored. Higher total scores mean greater self compassion, so the direction runs opposite to the FSCRS, PCI, PTQ and RRS, where higher means more difficulty.
B44: IPS items 2, 6 and 9 are reverse scored. The PPS has no reversed items. Both are free for research and clinical purposes per the author, with items from a CC BY article.
B45: GCS: the 5 items refer to a goal the client names, so the form must ask for that goal first; no verbatim published instructions were located. Items 1, 2 and 4 are reverse scored. Commercial use may need permission from Howard Klein. The items were corrected against Klein et al. (2001) after an aggregator site listed 2 items from the older 9 item scale.
B46: GADJ (Goal Adjustment Scale, coded GADJ to avoid confusion with Goal Attainment Scaling): 4 disengagement and 6 reengagement items, scored separately; items 2 and 3 are reverse scored. The published article carries no licence statement, and permission should be sought from Carsten Wrosch before paid use.
B47: BPNSFS: copyrighted by the Center for Self-Determination Theory. Academic use is free, but the Center’s terms state it may not be used for any commercial purpose without written permission, and paid coaching counts as commercial. Request a commercial licence through the Center before using it with clients. The 6 subscales of 4 items each are scored separately; satisfaction and frustration are distinct constructs with different links to wellbeing and ill being, so read them as a profile rather than combining them. No items are reverse scored. Reliability figures come from an open academia.edu copy of Chen et al. (2015) and should be checked against the journal version before quoting. It replaces the older 21 item Basic Psychological Need Satisfaction in General Scale, which fitted poorly.

Sheet Hub Library
A1: Code | B1: Hub id | C1: Name shown to clients | D1: Full instrument name | E1: Include in hub (Yes / No / Decide) | F1: Hub licence status (cleared / review / permission / excluded) | G1: Licence note | H1: Client sees strengths and focus (Yes / No) | I1: Flag items for Sarah (item numbers at threshold) | J1: Instructions shown to the client | K1: Minutes | L1: Notes
A2: ESQ-R | B2: esq-r | C2: Everyday executive skills | D2: Executive Skills Questionnaire - Revised (ESQ-R) | E2: Yes | F2: review | G2: Strait et al. (2020) scale, free to use; NovoPsych page carries a NovoPsych copyright notice. Confirm with Dr Peg Dawson or the authors before clearing. | H2: Yes | J2: Read each item and decide how often it's a problem for you. | K2: 5
A3: CFI | B3: cfi | C3: Thinking flexibly | D3: Cognitive Flexibility Inventory (CFI) | E3: Yes | F3: review | G3: Dennis and Vander Wal (2010); NovoPsych reproduction carries a NovoPsych copyright notice. Confirm author permission before clearing. | H3: Yes | J3: Please use the scale below to indicate the extent to which you agree or disagree with the following statements. | K3: 4
A4: ASRS | B4: asrs | C4: Attention and activity | D4: Adult ADHD Self-Report Scale (ASRS v1.1) | E4: Yes | F4: cleared | G4: Public domain WHO instrument, freely reproducible for clinical use. | H4: No | J4: Please answer the questions below, rating yourself on each of the criteria shown. As you answer each question, select the box that best describes how you have felt and conducted yourself over the past 6 months. | K4: 4
A5: SKS | B5: sks | C5: Knowing your strengths | D5: Strengths Knowledge Scale | E5: Yes | F5: review | G5: No explicit licence found; CAPP asserts copyright over the scales. Confirm before clearing. | H5: Yes | J5: Not stated on source | K5: 2
A6: SUS | B6: sus | C6: Using your strengths | D6: Strengths Use Scale | E6: Yes | F6: review | G6: No explicit licence found; CAPP asserts copyright over the scales. Confirm before clearing. | H6: Yes | J6: The following 14 questions ask about your strengths, that is, the things that you can do well or do best. | K6: 3
A7: SSES | B7: sses | C7: Confidence in your strengths | D7: Strengths Self-Efficacy Scale | E7: Yes | F7: review | G7: Distributed free for practitioner use by PositivePsychology.com; no explicit licence from the authors. Confirm before clearing. | H7: Yes | J7: First, please list your 5 signature strengths below: [space for 5 strengths]. How confident are you in your ability to .... | K7: 3
A8: CSES | B8: cses | C8: How you see yourself | D8: Core Self-Evaluations Scale | E8: Yes | F8: cleared | G8: Stated non proprietary and free to use without permission. | H8: Yes | J8: Not retrieved verbatim from a fetched source; the CSES PDF reproduces the item table and response scale but the source fetched did not include a printed respondent-facing preamble/instruction sentence. | K8: 3
A9: PES | B9: pes | C9: Feeling empowered at work | D9: Psychological Empowerment Scale | E9: Yes | F9: cleared | G9: Hosted freely by the author for research and practice use. | H9: Yes | J9: Listed below are a number of self-orientations that people may have with regard to their work role. Using the following scale, please indicate the extent to which you agree or disagree that each one describes your self-orientation. | K9: 3
A10: DASS-21 | B10: dass-21 | C10: How you have been feeling this week | D10: Depression Anxiety Stress Scales, 21 item version (DASS-21) | E10: Yes | F10: cleared | G10: Public domain per the official UNSW DASS site. | H10: No | I10: 10,17,21 at 2 | J10: Please read each statement and choose the answer that shows how much the statement applied to you over the past week. There are no right or wrong answers. Do not spend too much time on any statement. | K10: 4 | L10: Instructions reworded for the screen ("choose the answer" in place of "circle a number"); otherwise verbatim.
A11: PTQ | B11: ptq | C11: Repetitive thinking | D11: Perseverative Thinking Questionnaire | E11: Yes | F11: review | G11: Elsevier copyright on the article; no permission statement for practice use found. Confirm before clearing. | H11: Yes | J11: In this questionnaire, you will be asked to describe how you typically think about negative experiences or problems. Please read the following statements and rate the extent to which they apply to you when you think about negative experiences or problems. | K11: 4
A12: RRS | B12: rrs | C12: Responding to low mood | D12: Ruminative Responses Scale | E12: Yes | F12: review | G12: No explicit licence statement found. Confirm before clearing. Only Brooding and Reflection are scored. | H12: Yes | J12: Please read each of the items below and indicate whether you almost never, sometimes, often, or almost always think or do each one when you feel down, sad, or depressed. Please indicate what you generally do, not what you think you should do. | K12: 5
A13: FSCRS | B13: fscrs | C13: How you talk to yourself | D13: Forms of Self-Criticising/Attacking and Self-Reassuring Scale | E13: Yes | F13: review | G13: Author copyright notice (Gilbert et al., 2004); no explicit practice use grant found. Confirm before clearing. | H13: Yes | I13: 9 at 1 | J13: When things go wrong in our lives or don't work out as we hoped, and we feel we could have done better, we sometimes have negative and self-critical thoughts and feelings. These may take the form of feeling worthless, useless or inferior etc. However, people can also try to be supportive of themselves. Below are a series of thoughts and feelings that people sometimes have. Read each statement carefully and choose the answer that best describes how much each statement is true for you. | K13: 5 | L13: Instructions reworded for the screen ("choose the answer"); otherwise verbatim.
A14: PCI | B14: pci | C14: Perfectionistic thoughts | D14: Perfectionism Cognitions Inventory | E14: Yes | F14: review | G14: No explicit restriction found; Hewitt Lab hosts the document. Confirm before clearing. | H14: Yes | J14: Listed below are a variety of thoughts about perfectionism that sometimes pop into people's heads. Please read each thought and indicate how frequently, if at all, the thoughts occurred to you over the last week. | K14: 5
A15: SCS-SF | B15: scs-sf | C15: Self compassion | D15: Self-Compassion Scale – Short Form | E15: Yes | F15: review | G15: Author permits research use; practice use not addressed. Confirm with Dr Kristin Neff before clearing. | H15: Yes | J15: Please read each statement carefully before answering. Indicate how often you behave in the stated manner. | K15: 3
A16: BPNSFS | B16: bpnsfs | C16: What you need to feel at your best | D16: Basic Psychological Need Satisfaction and Frustration Scale (BPNSFS) | E16: Decide | F16: permission | G16: Copyright Center for Self-Determination Theory; written permission required for commercial use. | H16: Yes | J16: Below, we ask you about the kind of experiences you actually have in your life. Please read each of the following items carefully. You can choose from 1 to 5 to indicate the degree to which the statement is true for you at this point in your life. | K16: 5
A17: PPS | B17: pps | C17: Putting things off | D17: Pure Procrastination Scale | E17: Yes | F17: cleared | G17: Items published under CC BY (Svartdal and Steel, 2017). | H17: Yes | J17: Not stated on source | K17: 3
A18: IPS | B18: ips | C18: Delaying despite good intentions | D18: Irrational Procrastination Scale | E18: Yes | F18: cleared | G18: Items published under CC BY (Svartdal and Steel, 2017). | H18: Yes | J18: Not stated on source | K18: 2
A19: GSE | B19: gse | C19: Confidence in handling challenges | D19: General Self-Efficacy Scale | E19: Yes | F19: cleared | G19: Authors grant permission to use and reproduce. | H19: Yes | J19: Not stated on source | K19: 2
A20: GCS | B20: gcs | C20: Commitment to your goal | D20: Goal Commitment Scale (5-item unidimensional version) | E20: Decide | F20: permission | G20: No licence statement found; paywalled Elsevier article. Confirm before clearing. The form must ask the client to name a goal first. | H20: Yes | J20: Think of the main goal you are working on with Sarah. Answer each statement about that goal. | K20: 2 | L20: No verbatim published instructions exist. Draft wording for Sarah; the hub does not yet ask the client to type the goal.
A21: GADJ | B21: gadj | C21: Adjusting your goals | D21: Goal Adjustment Scale | E21: Decide | F21: permission | G21: Society for Personality and Social Psychology copyright; no permission statement found. Confirm before clearing. | H21: Yes | J21: "If I have to stop pursuing an important goal in my life . . ." This is the generic item stem used for all 10 items in Study 2 and Study 3, quoted verbatim from a footnote to Table 1 of Wrosch et al. (2003), fetched and confirmed in this session. In Study 1, the goal disengagement items only were instead presented against three separate situational stems, one of which is quoted verbatim in the article as: "If it becomes likely that I have to stop pursuing an important goal because I no longer have the opportunity to realize it . . ." | K21: 3

Sheet Hub Subscales
A1: Code | B1: Codebook subscale | C1: Hub subscale id | D1: Label shown to clients | E1: Scoring direction (difficulty / positive / none) | F1: Method (mean / sum) | G1: Lower band up to (blank = third of range) | H1: Upper band up to (blank = two thirds of range) | I1: Strength wording (client sees) | J1: Focus wording (client sees) | K1: Learning Hub topic | L1: Topic URL | M1: Notes
A2: ESQ-R | B2: Plan Management | C2: plan | D2: Planning and managing tasks | E2: difficulty | F2: mean | I2: You described planning and managing tasks as something that mostly goes smoothly for you. | J2: Planning and keeping track of tasks came up often in your answers. | K2: Planning and prioritising | L2: https://app.executiveframe.co.nz/hub/planning
A3: ESQ-R | B3: Time Management | C3: time | D3: Managing time | E3: difficulty | F3: mean | I3: You told us that keeping to time mostly works for you. | J3: Estimating and keeping to time came up as a difficulty in your answers. | K3: Time and estimating | L3: https://app.executiveframe.co.nz/hub/time
A4: ESQ-R | B4: Organization | C4: organisation | D4: Staying organised | E4: difficulty | F4: mean | I4: Keeping things and spaces in order mostly works for you. | J4: Keeping things and spaces in order came up as a difficulty in your answers. | K4: Organising your things and spaces | L4: https://app.executiveframe.co.nz/hub/organisation
A5: ESQ-R | B5: Emotional Regulation | C5: emotion | D5: Managing feelings | E5: difficulty | F5: mean | I5: You described managing strong feelings as something you handle well. | J5: Managing strong feelings came up as a difficulty in your answers. | K5: Managing feelings | L5: https://app.executiveframe.co.nz/hub/emotional-regulation
A6: ESQ-R | B6: Behavioral Regulation | C6: behaviour | D6: Pausing before acting | E6: difficulty | F6: mean | I6: Pausing before acting and sticking with a plan mostly works for you. | J6: Pausing before acting and sticking with a plan came up as a difficulty in your answers. | K6: Pausing and following through | L6: https://app.executiveframe.co.nz/hub/impulse-control
A7: CFI | B7: Alternatives | C7: alternatives | D7: Seeing other options | E7: positive | F7: mean | I7: You described finding other ways of seeing a situation as something that comes readily to you. | J7: Your answers suggest it can be hard to see other ways of reading a situation. | K7: Thinking flexibly | L7: https://app.executiveframe.co.nz/hub/flexible-thinking
A8: CFI | B8: Control | C8: control | D8: Seeing situations as workable | E8: positive | F8: mean | I8: You tend to see difficult situations as ones you can do something about. | J8: Your answers suggest difficult situations can feel outside your control. | K8: Thinking flexibly | L8: https://app.executiveframe.co.nz/hub/flexible-thinking
A9: ASRS | B9: Part A (Criterion / Screener) | C9: part-a | D9: Part A | E9: none | F9: sum | M9: Screener. Scored for Sarah only; the hub never shows this to the client.
A10: ASRS | B10: Part B (Additional Symptoms) | C10: part-b | D10: Part B | E10: none | F10: sum | M10: Scored for Sarah only.
A11: ASRS | B11: Inattentiveness | C11: inattention | D11: Inattention | E11: none | F11: sum | M11: Raw sum; the dichotomous symptom count is read from the shaded boxes by Sarah.
A12: ASRS | B12: Hyperactivity/Impulsivity - Motor | C12: motor | D12: Motor | E12: none | F12: sum | M12: Raw sum.
A13: ASRS | B13: Hyperactivity/Impulsivity - Verbal | C13: verbal | D13: Verbal | E13: none | F13: sum | M13: Raw sum.
A14: SKS | B14: Strengths Knowledge (total scale) | C14: total | D14: Knowing your strengths | E14: positive | F14: mean | I14: You have a clear sense of what your strengths are. | J14: Your answers suggest you are not yet sure what your strengths are, which is a good place to start. | K14: Finding your strengths | L14: https://app.executiveframe.co.nz/hub/strengths
A15: SUS | B15: Strengths Use (total scale) | C15: total | D15: Using your strengths | E15: positive | F15: mean | I15: You described using your strengths often, at work and beyond. | J15: Your answers suggest your strengths do not get much use day to day. | K15: Using your strengths | L15: https://app.executiveframe.co.nz/hub/strengths-use
A16: SSES | B16: Strengths Self-Efficacy (total scale) | C16: total | D16: Confidence in your strengths | E16: positive | F16: mean | I16: You feel confident applying your strengths when it counts. | J16: Your answers suggest you are not yet confident putting your strengths to use. | K16: Using your strengths | L16: https://app.executiveframe.co.nz/hub/strengths-use
A17: CSES | B17: Core Self-Evaluations (total scale, unidimensional) | C17: total | D17: How you see yourself | E17: positive | F17: mean | I17: You described a steady, positive view of yourself and what you can do. | J17: Your answers suggest your view of yourself can be harsh or uncertain. | K17: How you see yourself | L17: https://app.executiveframe.co.nz/hub/self-view
A18: PES | B18: Meaning | C18: meaning | D18: Meaning in your work | E18: positive | F18: mean | I18: Your work feels meaningful to you. | J18: Your answers suggest your work does not feel very meaningful at the moment. | K18: Meaning at work | L18: https://app.executiveframe.co.nz/hub/meaning
A19: PES | B19: Competence | C19: competence | D19: Confidence in your work | E19: positive | F19: mean | I19: You feel capable in your work. | J19: Your answers suggest you are not feeling confident in your work right now. | K19: Confidence at work | L19: https://app.executiveframe.co.nz/hub/competence
A20: PES | B20: Self-Determination | C20: autonomy | D20: Choice in how you work | E20: positive | F20: mean | I20: You have a good deal of say in how you do your work. | J20: Your answers suggest you have little say in how you do your work. | K20: Choice and autonomy at work | L20: https://app.executiveframe.co.nz/hub/autonomy
A21: PES | B21: Impact | C21: impact | D21: Influence at work | E21: positive | F21: mean | I21: You feel your work makes a difference where you are. | J21: Your answers suggest you feel your work has little influence on what happens around you. | K21: Influence at work | L21: https://app.executiveframe.co.nz/hub/impact
A22: DASS-21 | B22: Depression | C22: depression | D22: Depression | E22: difficulty | F22: sum | H22: 4 | M22: Raw sum of 7 items. Doubled score: normal 0 to 9. Sarah only.
A23: DASS-21 | B23: Anxiety | C23: anxiety | D23: Anxiety | E23: difficulty | F23: sum | H23: 3 | M23: Raw sum. Doubled score: normal 0 to 7. Sarah only.
A24: DASS-21 | B24: Stress | C24: stress | D24: Stress | E24: difficulty | F24: sum | H24: 7 | M24: Raw sum. Doubled score: normal 0 to 14. Sarah only.
A25: PTQ | B25: Core Characteristics of Repetitive Negative Thinking | C25: core | D25: Thoughts that go round | E25: difficulty | F25: mean | I25: Thoughts that repeat do not seem to take hold for long with you. | J25: Thoughts that go round and are hard to stop came up often in your answers. | K25: Repetitive thinking | L25: https://app.executiveframe.co.nz/hub/repetitive-thinking
A26: PTQ | B26: Unproductiveness | C26: unproductive | D26: Thinking that goes nowhere | E26: difficulty | F26: mean | I26: When you think things over, it tends to get you somewhere. | J26: Your answers suggest a lot of thinking that does not lead anywhere useful. | K26: Repetitive thinking | L26: https://app.executiveframe.co.nz/hub/repetitive-thinking
A27: PTQ | B27: Capturing Mental Capacity | C27: capacity | D27: Thinking that takes over | E27: difficulty | F27: mean | I27: Your thinking leaves you room for other things. | J27: Your answers suggest repetitive thinking takes up a lot of your mental space. | K27: Repetitive thinking | L27: https://app.executiveframe.co.nz/hub/repetitive-thinking
A28: RRS | B28: Brooding | C28: brooding | D28: Dwelling on what is wrong | E28: difficulty | F28: mean | I28: You do not tend to get stuck dwelling on what is wrong. | J28: Dwelling on what is wrong came up often in your answers. | K28: Getting unstuck from low mood | L28: https://app.executiveframe.co.nz/hub/brooding
A29: RRS | B29: Reflection | C29: reflection | D29: Reflecting on low mood | E29: none | F29: mean | M29: Reflection can be helpful or unhelpful; numbers only.
A30: RRS | B30: Depression-related items (not scored as a subscale) | C30: depressive | D30: Depression related items | E30: none | F30: mean | M30: Not recommended for coaching use; numbers only.
A31: FSCRS | B31: Inadequate Self | C31: inadequate | D31: Feeling not good enough | E31: difficulty | F31: mean | I31: You do not tend to come down hard on yourself when things go wrong. | J31: Feeling not good enough when things go wrong came up often in your answers. | K31: Self criticism | L31: https://app.executiveframe.co.nz/hub/self-criticism
A32: FSCRS | B32: Hated Self | C32: hated | D32: Harsh self attack | E32: difficulty | F32: mean | J32: Your answers include some very harsh thoughts about yourself, which Sarah will talk through with you. | K32: Self criticism | L32: https://app.executiveframe.co.nz/hub/self-criticism | M32: No strength wording; focus wording is deliberately gentle.
A33: FSCRS | B33: Reassured Self | C33: reassured | D33: Reassuring yourself | E33: positive | F33: mean | I33: You are able to be kind and reassuring to yourself when things go wrong. | J33: Your answers suggest reassuring yourself when things go wrong does not come easily yet. | K33: Self compassion | L33: https://app.executiveframe.co.nz/hub/self-compassion
A34: PCI | B34: Perfectionism Cognitions (total scale) | C34: total | D34: Perfectionistic thoughts | E34: difficulty | F34: mean | I34: Thoughts about needing to be perfect do not seem to feature much for you. | J34: Thoughts about needing to be perfect came up often in your answers. | K34: Perfectionism | L34: https://app.executiveframe.co.nz/hub/perfectionism
A35: SCS-SF | B35: Self-Kindness | C35: kindness | D35: Being kind to yourself | E35: positive | F35: mean | I35: You tend to treat yourself with kindness. | J35: Your answers suggest being kind to yourself does not come easily. | K35: Self compassion | L35: https://app.executiveframe.co.nz/hub/self-compassion
A36: SCS-SF | B36: Self-Judgment | C36: judgment | D36: Easing self judgement | E36: positive | F36: mean | I36: You tend not to judge yourself harshly. | J36: Your answers suggest you judge yourself harshly. | K36: Self compassion | L36: https://app.executiveframe.co.nz/hub/self-compassion | M36: Reverse scored, so higher is better.
A37: SCS-SF | B37: Common Humanity | C37: humanity | D37: Feeling you are not alone | E37: positive | F37: mean | I37: You see your struggles as part of being human. | J37: Your answers suggest your struggles feel like yours alone. | K37: Self compassion | L37: https://app.executiveframe.co.nz/hub/self-compassion
A38: SCS-SF | B38: Isolation | C38: isolation | D38: Feeling less isolated | E38: positive | F38: mean | I38: You tend not to feel cut off from others when things are hard. | J38: Your answers suggest you feel cut off from others when things are hard. | K38: Self compassion | L38: https://app.executiveframe.co.nz/hub/self-compassion | M38: Reverse scored, so higher is better.
A39: SCS-SF | B39: Mindfulness | C39: mindfulness | D39: Keeping perspective | E39: positive | F39: mean | I39: You tend to keep feelings in perspective. | J39: Your answers suggest difficult feelings can crowd out perspective. | K39: Self compassion | L39: https://app.executiveframe.co.nz/hub/self-compassion
A40: SCS-SF | B40: Over-Identification | C40: overidentification | D40: Not getting swept up | E40: positive | F40: mean | I40: You tend not to get swept up in difficult feelings. | J40: Your answers suggest difficult feelings can sweep you up. | K40: Self compassion | L40: https://app.executiveframe.co.nz/hub/self-compassion | M40: Reverse scored, so higher is better.
A41: BPNSFS | B41: Autonomy satisfaction | C41: autonomy-sat | D41: Feeling free to choose | E41: positive | F41: mean | I41: You feel free to choose how you live and work. | J41: Your answers suggest you do not feel free to choose how you live and work. | K41: Autonomy | L41: https://app.executiveframe.co.nz/hub/autonomy
A42: BPNSFS | B42: Autonomy frustration | C42: autonomy-frus | D42: Feeling pushed | E42: difficulty | F42: mean | I42: You do not feel pushed into things against your wishes. | J42: Feeling pushed into things came up often in your answers. | K42: Autonomy | L42: https://app.executiveframe.co.nz/hub/autonomy
A43: BPNSFS | B43: Relatedness satisfaction | C43: relatedness-sat | D43: Feeling connected | E43: positive | F43: mean | I43: You feel close to the people who matter to you. | J43: Your answers suggest you are not feeling close to the people who matter to you. | K43: Connection | L43: https://app.executiveframe.co.nz/hub/relatedness
A44: BPNSFS | B44: Relatedness frustration | C44: relatedness-frus | D44: Feeling left out | E44: difficulty | F44: mean | I44: You do not feel left out or distant from others. | J44: Feeling left out or distant from others came up often in your answers. | K44: Connection | L44: https://app.executiveframe.co.nz/hub/relatedness
A45: BPNSFS | B45: Competence satisfaction | C45: competence-sat | D45: Feeling capable | E45: positive | F45: mean | I45: You feel capable of what you set out to do. | J45: Your answers suggest you are not feeling capable of what you set out to do. | K45: Confidence | L45: https://app.executiveframe.co.nz/hub/competence
A46: BPNSFS | B46: Competence frustration | C46: competence-frus | D46: Doubting yourself | E46: difficulty | F46: mean | I46: You do not doubt your ability much. | J46: Doubting your ability came up often in your answers. | K46: Confidence | L46: https://app.executiveframe.co.nz/hub/competence
A47: PPS | B47: Pure Procrastination (total scale) | C47: total | D47: Putting things off | E47: difficulty | F47: mean | I47: Putting things off is not a big feature of how you work. | J47: Putting things off came up often in your answers. | K47: Getting started | L47: https://app.executiveframe.co.nz/hub/starting
A48: IPS | B48: Irrational Procrastination (total scale) | C48: total | D48: Delaying despite good intentions | E48: difficulty | F48: mean | I48: You mostly do what you intend to, when you intend to. | J48: Delaying things you meant to do came up often in your answers. | K48: Getting started | L48: https://app.executiveframe.co.nz/hub/starting
A49: GSE | B49: General Self-Efficacy (total scale) | C49: total | D49: Confidence in handling challenges | E49: positive | F49: mean | I49: You feel confident you can handle what comes your way. | J49: Your answers suggest you are not feeling confident about handling what comes your way. | K49: Confidence | L49: https://app.executiveframe.co.nz/hub/competence
A50: GCS | B50: Goal Commitment | C50: total | D50: Commitment to your goal | E50: positive | F50: mean | I50: You are firmly committed to the goal you named. | J50: Your answers suggest your commitment to the goal you named is wavering. | K50: Goals | L50: https://app.executiveframe.co.nz/hub/goals
A51: GADJ | B51: Goal Disengagement | C51: disengagement | D51: Letting go of goals | E51: none | F51: mean | M51: Neither high nor low is better in itself; numbers only.
A52: GADJ | B52: Goal Reengagement | C52: reengagement | D52: Finding new goals | E52: positive | F52: mean | I52: When a goal is out of reach you find new ones to pursue. | J52: Your answers suggest it is hard to find new goals when one is out of reach. | K52: Goals | L52: https://app.executiveframe.co.nz/hub/goals

Sheet Batteries
A1: Battery (form name) | B1: Notion tag | C1: Instrument codes | D1: Instruments | E1: Items in battery | F1: Administration time by instrument | G1: Report skill | H1: What it assesses | I1: Scoring and interpretation notes
A2: Executive Function Measures | B2: Executive Function (NT) | C2: ESQ-R | D2: Executive Skills Questionnaire - Revised (ESQ-R) | E2: =COUNTIF('Master Item List'!$A:$A,"ESQ-R") | F2: ESQ-R: 5 minutes | G2: ef-measures-report-nt | H2: Executive skills profile for clients without an ADHD diagnosis, locating difficulty across plan management, time management, organisation, emotional regulation and behavioural regulation. | I2: Single instrument battery. Higher ESQ-R scores mean more difficulty. The CFI was removed from this battery on 26 September 2026; check the report skill no longer expects it.
A3: Executive Function Measures (ADHD) | B3: Executive Function (ADHD) | C3: ASRS, ESQ-R | D3: Adult ADHD Self-Report Scale (ASRS v1.1) Executive Skills Questionnaire - Revised (ESQ-R) | E3: =COUNTIF('Master Item List'!$A:$A,"ASRS")+COUNTIF('Master Item List'!$A:$A,"ESQ-R") | F3: ASRS: 3 minutes ESQ-R: 5 minutes | G3: ef-measures-report-adhd | H3: The executive skills profile with current adult ADHD symptom screening added. Use for clients with a diagnosis or where ADHD is a live question. | I3: ASRS Part A of 14 or more is a positive screen, not a diagnosis. The CFI was removed from this battery on 26 September 2026. The report skill description still names the CFI and the ACOS-Self, neither of which is in this battery now; check the skill matches the form.
A4: Strengths Assessment | B4: Strengths | C4: SKS, SUS, SSES | D4: Strengths Knowledge Scale Strengths Use Scale Strengths Self-Efficacy Scale | E4: =COUNTIF('Master Item List'!$A:$A,"SKS")+COUNTIF('Master Item List'!$A:$A,"SUS")+COUNTIF('Master Item List'!$A:$A,"SSES") | F4: SKS: 2-3 minutes SUS: 3-5 minutes SSES: 3-5 minutes | G4: strengths-report | H4: Whether a client knows their strengths, uses them, and feels confident applying them. Suited to repeat administration to show change across a coaching engagement. | I4: No population norms; read against the client’s own baseline.
A5: Work Mindset Assessment | B5: Work Mindset | C5: CSES, PES | D5: Core Self-Evaluations Scale Psychological Empowerment Scale | E5: =COUNTIF('Master Item List'!$A:$A,"CSES")+COUNTIF('Master Item List'!$A:$A,"PES") | F5: CSES: 2-3 minutes PES: 3-5 minutes | G5: work-mindset-report | H5: General positive self appraisal alongside felt empowerment in a work or study role. | I5: The PES assumes a defined work role, so it suits employed and placement clients better than full time students.
A6: DASS-21 | B6: Single Measure | C6: DASS-21 | D6: Depression Anxiety Stress Scales, 21 item version (DASS-21) | E6: =COUNTIF('Master Item List'!$A:$A,"DASS-21") | F6: DASS-21: 4 minutes | G6: dass21-report | H6: Distress screening over the past week, to establish whether coaching can safely proceed and whether clinical input is needed. | I6: Screening only. Contains no suicide item and does not assess risk; items 10, 17 and 21 are followed up directly when endorsed at 2 or 3.
A7: Thinking Patterns | B7: Thinking Patterns | C7: PTQ, RRS | D7: Perseverative Thinking Questionnaire Ruminative Responses Scale | E7: =COUNTIF('Master Item List'!$A:$A,"PTQ")+COUNTIF('Master Item List'!$A:$A,"RRS") | F7: PTQ: Not stated in the source. A brief 15-item self-report measure, typically completed in a few minutes. RRS: Approximately 2 minutes (per NovoPsych). | G7: thinking-patterns-report | H7: The process of repetitive negative thinking rather than the resulting mood: overall perseverative thinking, and brooding versus reflective rumination. | I7: Only the RRS Brooding and Reflection subscales are recommended for coaching interpretation.
A8: Perfectionism | B8: Perfectionism | C8: CFI, PCI | D8: Cognitive Flexibility Inventory (CFI) Perfectionism Cognitions Inventory | E8: =COUNTIF('Master Item List'!$A:$A,"CFI")+COUNTIF('Master Item List'!$A:$A,"PCI") | F8: CFI: 3 minutes PCI: Approximately 4 minutes (per NovoPsych). | G8: perfectionism-report | H8: Frequency of perfectionistic self talk, paired with cognitive flexibility as the capacity that loosens it. | I8: PCI higher means more perfectionistic thinking; CFI higher means more flexibility.
A9: Self-Appraisal Assessment | B9: Self-Appraisal | C9: FSCRS, SCS-SF | D9: Forms of Self-Criticising/Attacking and Self-Reassuring Scale Self-Compassion Scale – Short Form | E9: =COUNTIF('Master Item List'!$A:$A,"FSCRS")+COUNTIF('Master Item List'!$A:$A,"SCS-SF") | F9: FSCRS: Not stated in the source. A brief 22-item self-report measure, typically completed in a few minutes. SCS-SF: Approximately 2 minutes (per NovoPsych). | G9: self-appraisal-report | H9: How a client talks to themselves when things go wrong: self critical and self reassuring forms from the FSCRS, and self compassion from the SCS-SF. | I9: FSCRS item 9 sits close to self harm content; frame with care. SCS-SF higher means more self compassion, the opposite direction to the FSCRS Inadequate and Hated Self subscales.
A10: Procrastination | B10: Procrastination | C10: PPS, IPS | D10: Pure Procrastination Scale Irrational Procrastination Scale | E10: =COUNTIF('Master Item List'!$A:$A,"PPS")+COUNTIF('Master Item List'!$A:$A,"IPS") | F10: PPS: 2-3 minutes IPS: 1-2 minutes | G10: procrastination-report | H10: General delay across decisions and tasks (PPS) and delay that the client recognises as harmful to them (IPS). | I10: IPS items 2, 6 and 9 are reverse scored.
A11: Goal Pursuit | B11: Goal Pursuit | C11: GSE, GCS, GADJ | D11: General Self-Efficacy Scale Goal Commitment Scale (5-item unidimensional version) Goal Adjustment Scale | E11: =COUNTIF('Master Item List'!$A:$A,"GSE")+COUNTIF('Master Item List'!$A:$A,"GCS")+COUNTIF('Master Item List'!$A:$A,"GADJ") | F11: GSE: 4 minutes average (per the official FU Berlin documentation) GCS: Not stated on source GADJ: Not stated on source | G11: No report skill yet | H11: General confidence in managing difficulty (GSE), commitment to a specific goal the client names (GCS), and the capacity to let go of unattainable goals and take up new ones (GADJ). | I11: GCS items refer to a goal the client names, so the form must ask for the goal first; GCS items 1, 2 and 4 are reverse scored. Score the 2 GADJ subscales separately; GADJ items 2 and 3 are reverse scored. Both the GCS and GADJ need author permission for paid use.
A12: Self-Determination | B12: Self Determination | C12: BPNSFS | D12: Basic Psychological Need Satisfaction and Frustration Scale (BPNSFS) | E12: =COUNTIF('Master Item List'!$A:$A,"BPNSFS") | F12: BPNSFS: Not stated on source | G12: self-determination-report | H12: Satisfaction and frustration of the needs for autonomy, competence and relatedness, to locate whether low motivation reflects unmet needs or actively thwarted ones. | I12: Keep the 6 subscales separate. Commercial use needs written permission from the Center for Self-Determination Theory.
A14: Instrument to battery map
A15: Instrument code | B15: Instrument | C15: Batteries using it
A16: ESQ-R | B16: Executive Skills Questionnaire - Revised (ESQ-R) | C16: Executive Function Measures Executive Function Measures (ADHD)
A17: CFI | B17: Cognitive Flexibility Inventory (CFI) | C17: Perfectionism
A18: ASRS | B18: Adult ADHD Self-Report Scale (ASRS v1.1) | C18: Executive Function Measures (ADHD)
A19: SKS | B19: Strengths Knowledge Scale | C19: Strengths Assessment
A20: SUS | B20: Strengths Use Scale | C20: Strengths Assessment
A21: SSES | B21: Strengths Self-Efficacy Scale | C21: Strengths Assessment
A22: CSES | B22: Core Self-Evaluations Scale | C22: Work Mindset Assessment
A23: PES | B23: Psychological Empowerment Scale | C23: Work Mindset Assessment
A24: DASS-21 | B24: Depression Anxiety Stress Scales, 21 item version (DASS-21) | C24: DASS-21
A25: PTQ | B25: Perseverative Thinking Questionnaire | C25: Thinking Patterns
A26: RRS | B26: Ruminative Responses Scale | C26: Thinking Patterns
... A35: GADJ | B35: Goal Adjustment Scale | C35: Goal Pursuit

Sheet Tally Prompt
A1: Tally form conversion prompt
A2: Use this prompt in Tally when converting an existing assessment form to a different battery. Copy the prompt from the single cell in row 5 (select the cell, copy, paste into Tally), then replace the final placeholder with the rows for each instrument in the battery. The Batteries tab lists which instruments belong to each form. For each instrument, paste from the Instrument Summary: Instrument Name and Code, Instructions / prompt, Response options, Reverse-scored items, Filler items, Subscales / structure and Total scoring; and from the Master Item List, all Item Text rows for that code in item number order.
A4: Prompt
A5: I want to convert this form to a different psychometric assessment. Keep the existing layout, branding and client details section exactly as they are, and make the following changes. 1. Title Change the form title to name the construct being measured, for example "Thinking Patterns Assessment". Use the plain construct name rather than instrument acronyms. 2. Introduction Keep the introductory paragraph, but rewrite its closing sentence so it explains why this assessment is being used and what it will help us understand. Keep the tone warm and plain, avoid clinical or diagnostic language, and write in UK English. 3. Client details Keep this section, its fields and its position unchanged. 4. Psychometric pages Delete the existing psychometric questions and replace them with the instruments below, one page per instrument. On each page: - Use the instrument's full name as the page heading. - Add the respondent instructions exactly as given. - Add every item exactly as worded and in the order given. Do not paraphrase, shorten or correct any item, including American spelling. - Number the items and make every item required. - Use the same question type for every item within an instrument. 5. Response scales Use the response scale given for each instrument, with the exact anchor labels and numeric values. Check that the scale fits the wording of the instructions (for example, a "how often" instruction needs a frequency scale, and a "how true" instruction needs an agreement or truth scale). Directly under the instructions on each page, add one sentence explaining how to use the scale and naming its anchors, for example: "Choose 1 if the statement is not at all true of you, through to 5 if it is completely true." 6. Scoring Add calculated fields that score each instrument according to the scoring information below. - Reverse score the listed items before adding them up. A reversed score is (scale maximum plus scale minimum) minus the response. - Record filler items but leave them out of every score. - Create one calculated field per subscale, plus a total only where the scoring information says a total is used. Where it says subscales are kept separate, do not create a total. - Name each calculated field with the instrument code and subscale, for example PTQ_Total or RRS_Brooding. - Keep every calculated field hidden from the respondent, so that no scores appear on the form or the thank you page. 7. Check back When you have finished, list back to me each page heading, the number of items per instrument, the response scale used, the reverse scored items, and each calculated field with its formula, so that I can check them against my codebook. Psychometric information: [Paste the codebook rows for each instrument here: name and code, instructions, response options, items, reverse scored items, filler items, subscales with item numbers, and total scoring.]
A7: Checks after Tally has built the form
A8: Item count on each page matches the Items in instrument column of the Instrument Summary.
A9: Item wording matches the Master Item List exactly, including spelling.
A10: Reverse scored items are reversed in the calculated fields, and filler items are excluded.
A11: The BPNSFS and RRS have subscale fields only, with no combined total.
A12: Calculated fields are hidden, so no scores appear on the form or the thank you page.
A13: Submit a test response and check each calculated field by hand against the scoring rules before sending the form to a client.

Sheet Instrument Summary
A1: Code | B1: Instrument Name | C1: Domain | D1: Availability | E1: Items in instrument | F1: Items in this codebook | G1: Construct measured | H1: Respondent | I1: Age range | J1: Administration time | K1: Cost and access | L1: Coaching application | M1: Purpose | N1: Instructions / prompt | O1: Response options | P1: Reverse-scored items | Q1: Filler items (not scored) | R1: Subscales / structure | S1: Total scoring | T1: Interpretation bands | U1: Cut-offs | V1: Normative data | W1: Psychometric properties | X1: Developer citation | Y1: Copyright and licensing | Z1: Source URL
A2: ESQ-R | B2: Executive Skills Questionnaire - Revised (ESQ-R) | C2: 1. Executive functioning and ADHD | D2: Free / open access | E2: 25 | F2: =COUNTIF('Master Item List'!$A:$A,$A2) | G2: Executive functioning skills, including plan and time management, organization, and emotional and behavioral regulation | H2: Self-report | I2: 14+ | J2: 5 minutes | K2: Included on NovoPsych with the permission of Dr Peg Dawson; blank form hosted free. Scoring and percentiles need a NovoPsych account. | L2: The core executive skills profile for coaching; the five subscales map directly onto coaching targets. Measures higher order skills rather than core executive functions. | M2: The ESQ-R is a 25-item self-report measure of executive functioning skills, including plan and time management, organization, and emotional and behavioral regulation. It was developed and published by Strait et al. (2020) and is included on NovoPsych with permission from Dr. Peg Dawson. It is intended to help identify specific areas of executive skill difficulty across five domains. | N2: Read each item and decide how often it's a problem for you. | O2: Never or rarely = 0 | Sometimes = 1 | Often = 2 | Very often = 3 | P2: None | Q2: None | R2: Plan Management (items 6-7, 12-14, 16-18, 22-24; n=11; range 0-33) Time Management (items 10-11, 15, 20; n=4; range 0-12) Organization (items 3, 8-9; n=3; range 0-9) Emotional Regulation (items 4-5, 21; n=3; range 0-9) Behavioral Regulation (items 1-2, 19, 25; n=4; range 0-12) | S2: Each item is rated on a 4-point Likert-type scale from 0 to 3 reflecting the frequency with which a respondent experiences a specific difficulty. Item scores are summed to produce a total score (range 0-75) and five subscale scores (Plan Management 0-33, Time Management 0-12, Organization 0-9, Emotional Regulation 0-9, Behavioral Regulation 0-12). Higher scores indicate more difficulties with executive functioning. No reverse-scored items were identified in the retrieved source material. | T2: Low Difficulties: ≤10th percentile - Low difficulties with executive functioning skills relative to the normative sample. Below Average Difficulties: 10th-24th percentile - Below average difficulties with executive functioning skills relative to the normative sample. Average Difficulties: 25th-75th percentile - Average difficulties with executive functioning skills relative to the normative sample. Above Average Difficulties: 76th-89th percentile - Above average difficulties with executive functioning skills relative to the normative sample. High Difficulties: ≥90th percentile - High difficulties with executive functioning skills relative to the normative sample. | U2: No diagnostic cut-off. Total score percentile bands: Low Difficulties (<=10th), Below Average (11th-24th), Average (25th-75th), Above Average (76th-89th), High (>=90th). Above Average or High suggests clinically significant executive functioning challenges. Subscale average ratings: No or Low Difficulty 0-1; Moderate Difficulty 1.01-1.99; High Difficulty 2-3. A change of 5 or more points on the total score is a Minimally Important Difference. | V2: Sample of 327 working adults in Malaysia (153 male, 171 female, 1 unknown; aged 23-80, M = 40.34, SD = 10.39) completing a modified ESQ-R (Nasir et al., 2021). Total M = 20.54 (SD 10.27); Plan Management M = 7.59 (SD 5.08); Time Management M = 3.03 (SD 2.24); Organization M = 2.57 (SD 1.96); Emotional Regulation M = 3.02 (SD 1.88); Behavioral Regulation M = 4.32 (SD 2.08). These means and SDs convert raw scores to percentiles. | W2: Internal consistency Cronbach's alpha = .91; test-retest reliability r = .70 (Strait et al., 2020). Factor alphas: Plan Management .89 (11 items), Time Management .74 (4), Organization .76 (3), Emotional Regulation .75 (3), Behavioral Regulation .65 (4). Convergent validity: Current Behavior Scale r = .74; Adult Executive Functioning Inventory r = .69. Discriminant validity: DASS-21 Depression r = .48, Anxiety r = .38, Stress r = .44; GAD-7 r = .45; PSS-10 r = .55. Academic engagement r = -.40. | X2: Developed by Dr. Peg Dawson (Smart But Scattered Kids). Original citation: Strait, J. E., Dawson, P., Walther, C. A. P., Strait, G. G., Barton, A. K., & McClain, M. B. (2020). Refinement and psychometric evaluation of the Executive Skills Questionnaire-Revised. Contemporary School Psychology, 24, 378-388. https://doi.org/10.1007/s40688-018-00224-x | Y2: © 2026 Copyright – NovoPsych – All rights reserved. The ESQ-R was developed and published by Strait et al. (2020) and is included on NovoPsych with permission from Dr. Peg Dawson. | Z2: https://novopsych.com/assessments/formulation/executive-skills-questionnaire-revised-esq-r/
A3: CFI | B3: Cognitive Flexibility Inventory (CFI) | C3: 1. Executive functioning and ADHD | D3: Free / open access | E3: 20 | F3: =COUNTIF('Master Item List'!$A:$A,$A3) | G3: Cognitive flexibility - the ability to perceive multiple alternative explanations for life occurrences and human behaviour, generate multiple alternative solutions to difficult situations, and perceive difficult situations as controllable | H3: Self-report | I3: 18+ | J3: 3 minutes | K3: Published in Dennis and Vander Wal (2010); blank form hosted free on NovoPsych. | L3: Measures cognitive flexibility, useful for tracking response to reframing and problem solving work. Scored in the opposite direction to the ESQ-R. | M3: The CFI is a 20-item self-report measure used to monitor how often individuals engaged in cognitive behavioural thought challenging interventions. Cognitive flexibility is a core skill targeted in cognitive behavioral therapy that enables adaptive thinking during stressful life events and helps individuals avoid maladaptive thinking patterns. | N3: Please use the scale below to indicate the extent to which you agree or disagree with the following statements. | O3: Strongly disagree = 1 | Disagree = 2 | Somewhat disagree = 3 | Neutral = 4 | Somewhat agree = 5 | Agree = 6 | Strongly agree = 7 | P3: 2, 4, 7, 9, 11, 17 | Q3: None | R3: Alternatives (items 1, 3, 5-6, 8, 10, 12-14, 16, 18-20; n=13; range 13-91) Control (items 2, 4, 7, 9, 11, 15, 17; n=7; range 7-49) | S3: Each item is rated on a 7-point Likert scale from 1 (Strongly disagree) to 7 (Strongly agree). Items 2, 4, 7, 9, 11, and 17 are reverse scored. Item scores are summed to produce a total CFI score and two subscale scores (Alternatives and Control). A higher score indicates more cognitive flexibility. | T3: Clinically significant inflexibility: Below approximately the 25th percentile - Cognitive inflexibility of clinical significance; a target for CBT. Average: Around the 50th percentile - More cognitive flexibility than 50 per cent of the normative sample. High flexibility: Upper percentiles - Higher likelihood of adaptive responses to difficult life experiences. | U3: No formal diagnostic cut-off. Percentiles below approximately 25 represent clinically significant cognitive inflexibility, which would be important to target within cognitive behavioural therapy. | V3: Sample of 196 university students (Dennis & Vander Wal, 2010): CFI total M = 102.98 (SD = 13.91); Alternatives M = 67.59 (SD = 9.41); Control M = 35.35 (SD = 7.02). | W3: Test-retest reliability: total r = .81; Alternatives r = .75; Control r = .77 (Dennis & Vander Wal, 2010). Internal consistency: Alternatives alpha = .91; Control alpha = .86; total alpha = .90. Convergent construct validity established through associations with other measures of cognitive flexibility, depressive symptomatology and coping (Dennis & Vander Wal, 2010). The CFI differentiates a clinical group (anxiety and depression) from a non-clinical sample, with the clinical group scoring significantly lower on total and subscale scores (Johnco, Wuthrich, & Rapee, 2014). | X3: Dennis, J. P., & Vander Wal, J. S. (2010). The cognitive flexibility inventory: Instrument development and estimates of reliability and validity. Cognitive Therapy and Research, 34(3), 241-253. https://doi.org/10.1007/s10608-009-9276-4 | Y3: © 2026 Copyright – NovoPsych – All rights reserved. Sample report footer: Copyright 2022 NovoPsych Pty Ltd. | Z3: https://novopsych.com/assessments/formulation/cognitive-flexibility-inventory-cfi/
A4: ASRS | B4: Adult ADHD Self-Report Scale (ASRS v1.1) | C4: 1. Executive functioning and ADHD | D4: Free / open access | E4: 18 | F4: =COUNTIF('Master Item List'!$A:$A,$A4) | G4: Attention Deficit Hyperactivity Disorder (ADHD) symptoms in adults, spanning inattentiveness and hyperactivity/impulsivity (including motor and verbal components) | H4: self-report | I4: 18+ | J4: 3 minutes | K4: Public domain WHO instrument. Blank form hosted free on NovoPsych; scoring and reports need a NovoPsych account. | L4: Screening and severity measure for current adult ADHD symptoms; pairs with the WURS-25 for childhood history. Not a diagnostic instrument on its own. | M4: The ASRS v1.1 is an 18-item self-report questionnaire designed to assess ADHD symptoms in adults. It is based on the World Health Organization Composite International Diagnostic Interview (2001) and is worded to be consistent with both DSM-IV and DSM-5-TR criteria as they manifest in adults. It is intended as a screening tool used alongside clinical interview and other measures (e.g. the WURS for childhood history) rather than as a standalone diagnostic instrument. | N4: Please answer the questions below, rating yourself on each of the criteria shown. As you answer each question, select the box that best describes how you have felt and conducted yourself over the past 6 months. | O4: Never = 0 | Rarely = 1 | Sometimes = 2 | Often = 3 | Very Often = 4 | P4: None | Q4: None | R4: Part A (Criterion / Screener) (items 1-6; n=6; range 0-24) Part B (Additional Symptoms) (items 7-18; n=12; range 0-48) Inattentiveness (items 1-4, 7-11; n=9; range 0-9 (dichotomous symptom count)) Hyperactivity/Impulsivity - Motor (items 5-6, 12-14; n=5; range 0-5 (dichotomous symptom count)) Hyperactivity/Impulsivity - Verbal (items 15-18; n=4; range 0-4 (dichotomous symptom count)) | S4: As of the 2024 update, each of the 18 items is scored on a 5-point Likert scale (Never=0, Rarely=1, Sometimes=2, Often=3, Very Often=4). Part A = sum of items 1-6 (range 0-24). Part B = sum of items 7-18 (range 0-48). Total = sum of all 18 items (range 0-72). The original dichotomous (0/1) scoring is still used separately to calculate the 'percent of symptoms endorsed' for subtype/subscale reporting. | T4: Part A - Low: 0-9 - Not consistent with an ADHD diagnosis. Part A - Mild to Moderate: 10-13 - Below the screening threshold; some symptoms reported. Part A - High: 14-17 - Clinically significant. Symptom profile consistent with a DSM-5-TR ADHD diagnosis in adults. Part A - Very High: 18-24 - Clinically significant; symptoms endorsed at high frequency. Part B - Low: 0-19 - Low additional symptom burden. Part B - Mild to Moderate: 20-26 - Below the clinically significant range. Part B - High: 27-32 - Clinically significant. Part B - Very High: 33-48 - Clinically significant; high additional symptom burden. Total - Low: 0-30 - Low overall symptom burden. Total - Mild to Moderate: 31-39 - Below the range typical of adults with ADHD. Total - High: 40-49 - At or above the 79th percentile; in most cases someone with ADHD will score in this range or above. Total - Very High: 50-72 - Very high overall symptom burden. | U4: Part A >= 14 constitutes a positive screen and a symptom profile consistent with a DSM-5-TR adult ADHD diagnosis (Adler et al., 2006; Kessler et al., 2007; Harvard Medical School, 2024). Part B >= 27 is clinically significant. A total score at or above the 79th percentile (raw >= 40) typically indicates ADHD. Kessler et al. (2007) four-level Part A classification: 0-9, 10-13, 14-17, 18-24 (AUC = 0.90). Always use alongside clinical interview. | V4: Adler et al. (2018/2019) sample of 22,397 adults, 465 (2.1%) self-reporting a physician ADHD diagnosis. NovoPsych recalculated summed means/SDs (Likert scoring), accounting for inter-item correlations (r = 0.32 within parts, r = 0.74 between Parts A and B). ADHD group (n = 465): Part A M = 16.71 (SD 5.07); Part B M = 32.74 (SD 9.16); Total M = 49.45 (SD 13.36). Community sample (n = 21,932): Part A M = 10.88 (SD 3.76); Part B M = 21.60 (SD 6.69); Total M = 32.48 (SD 9.80). | W4: Internal consistency: Cronbach's alpha = .88 in adult ADHD patients (Adler et al., 2006); .952 for the full scale (Brevik et al., 2020). Concurrent validity with clinician-rated symptoms r = .84 (Adler et al., 2006). Diagnostic accuracy: AUC = .904 for the 18-item scale and .903 for the six Part A items (Brevik et al., 2020); AUC = .90 for the Kessler et al. (2007) four-level Part A classification. Under the previous scoring convention, sensitivity 1.0, specificity .71, PPP .52, NPP 1.0 (Hines, King & Curry, 2012). Combined with the WURS-25, AUC = .964. Factor structure: CFA in over 1,000 adults identified three factors - Inattentiveness, Motor Hyperactivity/Impulsivity, Verbal Hyperactivity/Impulsivity (Stanton et al., 2018). | X4: Kessler, R. C., Adler, L., Ames, M., Demler, O., Faraone, S., Hiripi, E., Howes, M. J., Jin, R., Secnik, K., Spencer, T., Ustun, T. B., & Walters, E. E. (2005). The World Health Organization Adult ADHD Self-Report Scale (ASRS): a short screening scale for use in the general population. Psychological Medicine, 35(2), 245-256. https://doi.org/10.1017/s0033291704002892 | Y4: Public-domain WHO instrument (ASRS v1.1 Symptom Checklist). Freely reproducible for clinical and research use; NovoPsych hosts the blank form as a public PDF. | Z4: https://novopsych.com/assessments/diagnosis/adult-adhd-self-report-scale-asrs/
A5: SKS | B5: Strengths Knowledge Scale | C5: 2. Strengths knowledge, use and support at work | D5: Free / open access | E5: 8 | F5: =COUNTIF('Master Item List'!$A:$A,$A5) | G5: Perceived self-knowledge of one's own personal strengths, i.e. the extent to which a person is aware of what they do best. | H5: Self-report | I5: Adults and university students; used in adolescent samples (secondary school age) in later validations, but the original 2007 development sample was working adults | J5: 2-3 minutes | K5: No licence fee or permission is required to use the SKS in coaching practice. The scale was published in full within the original journal article (Govindji & Linley, 2007, International Coaching Psychology Review, a BPS Special Group in Coaching Psychology publication) and has since been reproduced verbatim in several open-access peer-reviewed validation papers (e.g. the Frontiers in Psychology 2023 Spanish validation used as the source for this record). A practitioner can administer it as a simple paper or online 7-point rating form; no test manual, scoring software or purchase is needed. The original 2007 article itself is not reliably available as an open PDF (International Coaching Psychology Review back issues are not consistently hosted online), so items here were transcribed from an open-access reproduction rather than the original publication. | L5: The SKS is useful early in strengths coaching to establish a baseline of how well a client can already name and recognise their own best qualities, which shapes whether initial sessions should focus on strength identification (e.g. via VIA or Realise2) before moving to strengths use. Low scores flag clients who may benefit from structured strength-spotting exercises, feedback from others, or a formal strengths assessment before goal-setting. Its main limit is that it only captures self-perceived awareness, not accuracy of that self-knowledge, so it should be paired with an objective strengths measure or 360-degree feedback rather than used alone to confirm what a client's real strengths are. | M5: The SKS was developed by Govindji and Linley (2007) to measure the degree to which individuals know their own strengths, as a companion construct to strengths use. It was designed for use in positive psychology and coaching research examining how strengths knowledge and strengths use relate to well-being outcomes (subjective well-being, psychological well-being and vitality). | N5: Not stated on source | O5: Strongly disagree = 1 | 2 = 2 | 3 = 3 | 4 = 4 | 5 = 5 | 6 = 6 | Strongly agree = 7 | P5: None | Q5: None | R5: Strengths Knowledge (total scale) (items 1-8; n=8; range 8-56) | S5: Sum (or mean) of the 8 item ratings. Higher total scores indicate greater self-perceived knowledge of one's own strengths. No published reverse-scored items were identified for this scale in the sources reviewed. | T5: Not stated on source | U5: No clinical or normative cut-off scores have been published for the SKS. It is used as a continuous research/coaching variable, typically compared against a client's own baseline over time rather than against population norms. | V5: No formal normative tables were located. Reported sample means come from individual studies using varied populations (e.g. UK working adults in the original 2007 study; Chinese adolescents in Duan, Li & Mu, 2018, Journal of Happiness Studies; Spanish-speaking adults in the 2023 Frontiers validation) and are not interchangeable as norms. | W5: Internal consistency has repeatedly been reported as high: Cronbach's alpha = .90 for the English-language items in a 2023 Spanish validation study (Frontiers in Psychology, fpsyg.2023.1086510), which also confirmed a single-factor structure. The original Govindji & Linley (2007) paper is reported in secondary sources to have found good reliability and significant positive correlations between strengths knowledge, strengths use, subjective well-being, psychological well-being and vitality, but the exact original alpha coefficient could not be independently confirmed from a source directly accessed for this record. | X5: Govindji, R., & Linley, P. A. (2007). Strengths use, self-concordance and well-being: Implications for strengths coaching and coaching psychologists. International Coaching Psychology Review, 2(2), 143-153. | Y5: No explicit copyright statement, licence, or restriction on use was found for the SKS in any source reviewed. It is a short academic research scale that has been freely reprinted in full within multiple peer-reviewed, open-access journal articles without any stated permission requirement; practitioners typically cite Govindji and Linley (2007) as the source when using it. This should not be taken as a formal confirmation of public-domain status, only as the licensing position actually found. | Z5: https://www.frontiersin.org/journals/psychology/articles/10.3389/fpsyg.2023.1086510/full
A6: SUS | B6: Strengths Use Scale | C6: 2. Strengths knowledge, use and support at work | D6: Free / open access | E6: 14 | F6: =COUNTIF('Master Item List'!$A:$A,$A6) | G6: Perceived deployment of one's own personal strengths in daily life, i.e. the extent to which a person actively uses what they do best across situations. | H6: Self-report | I6: Adults and university students; used in adolescent samples (secondary school age) in later validations, but the original 2007 development sample was working adults | J6: 3-5 minutes | K6: No licence fee or permission is required to use the SUS in coaching practice. The scale was published in full within the original journal article (Govindji & Linley, 2007, International Coaching Psychology Review, a BPS Special Group in Coaching Psychology publication) and has since been reproduced verbatim in several open-access peer-reviewed validation papers (e.g. the Frontiers in Psychology 2023 Spanish validation used as the source for this record). It can be administered as a simple paper or online 7-point rating form; no manual, scoring software or purchase is needed. The original 2007 article itself is not reliably available as an open PDF (International Coaching Psychology Review back issues are not consistently hosted online), so items here were transcribed from an open-access reproduction rather than the original publication. | L6: The SUS is well suited to tracking a client's progress in strengths coaching over time, since it directly measures how often and how naturally strengths are being deployed at work, study and in life generally, which is the practical outcome most strengths coaching aims to move. It works well as a short pre/post measure around a block of coaching focused on applying identified strengths to goals. Its limit is that it assumes the client already knows what their strengths are (it should usually follow, not replace, a strengths-identification step such as VIA or the SKS) and it captures frequency and ease of use rather than the fit or appropriateness of how strengths are being applied. | M6: The SUS was developed by Govindji and Linley (2007) to measure the degree to which individuals use their strengths in everyday life, for use in positive psychology and coaching research examining how strengths use relates to self-concordance and to well-being outcomes (subjective well-being, psychological well-being and vitality). | N6: The following 14 questions ask about your strengths, that is, the things that you can do well or do best. | O6: Strongly disagree = 1 | 2 = 2 | 3 = 3 | 4 = 4 | 5 = 5 | 6 = 6 | Strongly agree = 7 | P6: None | Q6: None | R6: Strengths Use (total scale) (items 1-14; n=14; range 14-98) | S6: Sum (or mean) of the 14 item ratings. Higher total scores indicate greater self-reported use of personal strengths in daily life. No reverse-scored items were identified for this scale in the sources reviewed. | T6: Not stated on source | U6: No clinical or normative cut-off scores have been published for the SUS. It is used as a continuous research/coaching variable, typically tracked against a client's own baseline over time rather than against population norms. | V6: No formal normative tables were located. Reported sample means come from individual studies using varied populations (e.g. UK working adults in the original 2007 study; Chinese adolescents in Duan, Li & Mu, 2018, Journal of Happiness Studies; Spanish-speaking adults in the 2023 Frontiers validation) and are not interchangeable as norms. | W6: Internal consistency has repeatedly been reported as very high: Cronbach's alpha = .95 for the English-language items in a 2023 Spanish validation study (Frontiers in Psychology, fpsyg.2023.1086510), which also confirmed a single-factor structure. The original Govindji & Linley (2007) paper is reported in secondary sources to have found good reliability and significant positive correlations between strengths use, self-concordance, subjective well-being, psychological well-being and vitality, but the exact original alpha coefficient could not be independently confirmed from a source directly accessed for this record. | X6: Govindji, R., & Linley, P. A. (2007). Strengths use, self-concordance and well-being: Implications for strengths coaching and coaching psychologists. International Coaching Psychology Review, 2(2), 143-153. | Y6: No explicit copyright statement, licence, or restriction on use was found for the SUS in any source reviewed. It is a short academic research scale that has been freely reprinted in full within multiple peer-reviewed, open-access journal articles without any stated permission requirement; practitioners typically cite Govindji and Linley (2007) as the source when using it. This should not be taken as a formal confirmation of public-domain status, only as the licensing position actually found. | Z6: https://www.frontiersin.org/journals/psychology/articles/10.3389/fpsyg.2023.1086510/full
A7: SSES | B7: Strengths Self-Efficacy Scale | C7: 2. Strengths knowledge, use and support at work | D7: Free / open access | E7: 11 | F7: =COUNTIF('Master Item List'!$A:$A,$A7) | G7: Perceived self-efficacy (confidence) in one's ability to identify, apply and use one's personal strengths across everyday situations, at work or study, and in pursuit of goals. | H7: Self-report | I7: Adults; validated with U.S. college students and working adults, applicable to late-secondary and university-age coaching clients | J7: 3-5 minutes | K7: The SSES is free to use for practice and research; the full 11-item form (with its instructions, five-signature-strengths preamble, and 10-point response scale) is published as an open-access downloadable PDF by PositivePsychology.com, and the same item wording is corroborated by an independent academic reproduction. No licence fee or formal permission is required, though practitioners should cite Tsai, Chaichanasakul, Zhao, Flores and Lopez (2014) as the scale's developers. The original peer-reviewed validation article is behind a SAGE subscription paywall (Journal of Career Assessment). | L7: The SSES is a good fit for strengths-based career and academic coaching because it measures confidence in actually applying strengths, which is the practical skill most coaching aims to build, and it can be re-administered after a coaching block to check whether a client's confidence in using their strengths has shifted. Because it asks respondents to first name their own five signature strengths, it works well paired with a prior strengths-identification step (VIA, Realise2, or the SKS/SUS above). Its limit is that it measures perceived confidence rather than actual competent strengths use, so a client can score highly while still using strengths in an unhelpful or overextended way, and low scores need follow-up to distinguish a genuine skills gap from low self-belief alone. | M7: The SSES was developed by Tsai, Chaichanasakul, Zhao, Flores and Lopez (2014) to give career counsellors, educators and researchers a brief measure of an individual's confidence in their ability to build on and apply their personal strengths in daily life, extending Bandura's self-efficacy framework to the strengths domain. | N7: First, please list your 5 signature strengths below: [space for 5 strengths]. How confident are you in your ability to .... | O7: Not confident at all = 1 | 2 = 2 | 3 = 3 | 4 = 4 | Moderately confident = 5 | 6 = 6 | 7 = 7 | 8 = 8 | 9 = 9 | Extremely confident = 10 | P7: None | Q7: None | R7: Strengths Self-Efficacy (total scale) (items 1-11; n=11; range 11-110) | S7: Sum the 11 item scores for a total (range 11-110); a weighted/mean score can also be calculated by dividing the total by 11. Higher scores indicate greater confidence in using one's strengths. No items are reverse-scored. | T7: Not stated on source | U7: No clinical or normative cut-off scores have been published for the SSES. It is intended as a continuous measure for research and for tracking an individual's own change over time, not for categorical classification. | V7: No published normative tables were located. The original validation samples were U.S. adults: 275 in the exploratory factor analysis phase, 302 in the confirmatory phase, and 36 in a 3-week test-retest reliability subsample. | W7: In the original validation (Tsai et al., 2014), exploratory factor analysis on the first adult sample (n = 275) supported a single general strengths-self-efficacy factor with internal consistency of alpha = .96; confirmatory factor analysis on a second sample (n = 302) confirmed the one-factor structure with alpha = .95. A 3-week test-retest reliability check (n = 36) showed stable scores over time. Validity evidence included moderate positive correlations with self-esteem and life satisfaction, and a weak relationship with social desirability, supporting discriminant validity from mere impression management. | X7: Tsai, C.-L., Chaichanasakul, A., Zhao, R., Flores, L. Y., & Lopez, S. J. (2014). Development and validation of the Strengths Self-Efficacy Scale (SSES). Journal of Career Assessment, 22(2), 221-232. https://doi.org/10.1177/1069072713493761 | Y7: No explicit copyright restriction or paid-licence requirement was found; PositivePsychology.com distributes the full instrument as a free downloadable PDF for practitioner use, and an independent academic reproduction (academia.edu) carries identical item wording, both without a stated permissions requirement beyond citing the original authors. The peer-reviewed source article remains behind a SAGE subscription paywall. This reflects the licensing position actually found, not a confirmed public-domain status. | Z7: https://positivepsychology.com/wp-content/uploads/The-Strengths-Self-efficacy-Scale.pdf
A8: CSES | B8: Core Self-Evaluations Scale | C8: 3. Adjacent occupational and wellbeing | D8: Free / open access | E8: 12 | F8: =COUNTIF('Master Item List'!$A:$A,$A8) | G8: Core self-evaluations: a broad, fundamental positive self-appraisal trait combining self-esteem, generalised self-efficacy, internal locus of control and low neuroticism (emotional stability). | H8: Self-report | I8: Working adults (Samples 1-2 of the original validation); also validated with university undergraduates (Samples 3-4). Suitable for university-age and early-career coaching clients. | J8: 2-3 minutes | K8: The scale is explicitly stated by the developers to be non-proprietary and free to use without permission. The full 12-item scale, with response format and scoring key, is reproduced in an open PDF of the original SIOP conference/journal materials. | L8: The CSES is useful as a brief baseline measure of a student or early-career client's general positive self-appraisal (self-esteem, self-efficacy, sense of control) at the start of a coaching relationship, and can flag when low scores on 'control' or 'competence' items point to executive-function or confidence work rather than a skills gap. It is not a strengths-identification tool and should not be presented to a client as diagnostic; its brevity and free licence make it practical for repeat use, but coaches should be alert that several reverse-scored items touch on depressed mood and hopelessness, which needs sensitive framing with any client where wellbeing is a live concern. | M8: Judge, Erez, Bono and Thoresen developed the CSES to provide a direct, parsimonious measure of core self-evaluations, a higher-order trait they argued underlies self-esteem, generalised self-efficacy, locus of control and neuroticism, and which predicts job and life satisfaction and job performance. | N8: Not retrieved verbatim from a fetched source; the CSES PDF reproduces the item table and response scale but the source fetched did not include a printed respondent-facing preamble/instruction sentence. | O8: Strongly Disagree = 1 | Disagree = 2 | Neutral = 3 | Agree = 4 | Strongly Agree = 5 | P8: 2, 4, 6, 8, 10, 12 | Q8: None | R8: Core Self-Evaluations (total scale, unidimensional) (items 1-12; n=12; range 12-60) | S8: Reverse-score items 2, 4, 6, 8, 10 and 12 (6 minus the raw response on the 1-5 scale), then sum or average all 12 items. Higher scores indicate more positive core self-evaluations. | T8: Not stated on source | U8: No published clinical or normative cut-off scores; intended as a continuous individual-differences measure for research and comparison, not categorical classification. | V8: No population percentile norm tables were retrieved. Original validation means/SDs by sample were not reproduced in the source fetched; sample sizes and composition were: Sample 1, N = 280, US food-service company employees (roles from truck driver to manager); Sample 2, N = 175, pharmaceutical sales representatives, mean age 42.1; Sample 3, N = 265 (T1) and 205 (T2), undergraduates; Sample 4, N = 126, undergraduates. | W8: Internal consistency (Cronbach's alpha): Sample 1 = .85; Sample 2 = .83; Sample 3 T1 = .85, T2 = .87; Sample 4 (self-report) = .83, (other-report) = .81. Test-retest reliability over one month (Sample 3) = .81. Inter-rater (self/significant-other) agreement ICC = .43. Convergent validity (corrected correlations): self-esteem .80-.92, generalised self-efficacy .78-.90, neuroticism -.67 to -.84, locus of control .41-.62. Criterion validity (corrected correlations): job satisfaction .49-.59, job performance .26-.27, life satisfaction .53-.66. (Judge, Erez, Bono & Thoresen, 2003, Table 4.) | X8: Judge, T. A., Erez, A., Bono, J. E., & Thoresen, C. J. (2003). The Core Self-Evaluations Scale: Development of a measure. Personnel Psychology, 56(2), 303-331. https://doi.org/10.1111/j.1744-6570.2003.tb00152.x | Y8: "This measure is non-proprietary (free) and may be used without permission," as stated in the source fetched. | Z8: http://ionilies.com/SIOP03/Files/CSES.pdf
A9: PES | B9: Psychological Empowerment Scale | C9: 3. Adjacent occupational and wellbeing | D9: Free / open access | E9: 12 | F9: =COUNTIF('Master Item List'!$A:$A,$A9) | G9: Psychological empowerment at work, a motivational construct with four cognitive dimensions: meaning, competence, self-determination and impact. | H9: Self-report, employed adults | I9: Working adults; original validation used middle managers and industrial-firm employees. Applicable to early-career and internship-stage clients holding a defined work role. | J9: 3-5 minutes | K9: The instrument is hosted freely by the developer, Gretchen Spreitzer, on her own university web page for research and practice use, with no stated fee or formal permission process. | L9: This scale works well in coaching to make explicit which of the four empowerment dimensions (meaning, competence, self-determination, impact) is weakest for a client in a job, internship or leadership role, giving a concrete focus for goal-setting. It is designed for someone already in a defined work role with a 'department' or team, so it fits early-career and placement clients better than full-time students without paid work, and it measures a felt cognitive state rather than actual job conditions, so a low score should prompt exploration of both the client's perception and the realities of their role rather than being taken as a fixed trait. | M9: Spreitzer (1995) developed this scale to operationalise and measure psychological empowerment as a multidimensional motivational construct in the workplace, validating it as an antecedent of managerial effectiveness and innovation. | N9: Listed below are a number of self-orientations that people may have with regard to their work role. Using the following scale, please indicate the extent to which you agree or disagree that each one describes your self-orientation. | O9: Very Strongly Disagree = 1 | Strongly Disagree = 2 | Disagree = 3 | Neutral = 4 | Agree = 5 | Strongly Agree = 6 | Very Strongly Agree = 7 | P9: None | Q9: None | R9: Meaning (items 1-3; n=3; range 3-21 (mean 1-7)) Competence (items 4-6; n=3; range 3-21 (mean 1-7)) Self-Determination (items 7-9; n=3; range 3-21 (mean 1-7)) Impact (items 10-12; n=3; range 3-21 (mean 1-7)) | S9: Each subscale is scored as the mean of its 3 items (range 1-7). An overall empowerment score can be computed as the mean of the four subscale means, as the source document itself instructs: "You may use the subdimensions individually (taking the mean of the 3 items measuring one dimension) or take the mean of the 4 subdimension means to create an overall empowerment score." | T9: Not stated on source | U9: No published clinical or normative cut-off scores; intended as a continuous research and diagnostic measure, not categorical classification. | V9: No specific normative table (means/SDs) was retrieved. The instrument page states the scale has been "used successfully in more than 50 different studies" since the original 1995 validation, which used two working-adult field samples (insurance-company middle managers and a Fortune 50 industrial firm), with typical test-retest reliability and validity coefficients around .80 across studies. | W9: Test-retest reliability described on the source page as "strong," with validity estimates for the four dimensions "typically around .80" across the more than 50 studies that have used the scale. Exact original-validation alpha coefficients per subscale were not reproduced on the instrument page fetched. | X9: Spreitzer, G. M. (1995). Psychological empowerment in the workplace: Dimensions, measurement, and validation. Academy of Management Journal, 38(5), 1442-1465. https://doi.org/10.2307/256865 | Y9: Hosted freely by the author for research and practice use; no explicit restriction or fee is stated on the page. | Z9: https://webuser.bus.umich.edu/spreitze/Pdfs/EmpowerInstrument.pdf
A10: DASS-21 | B10: Depression Anxiety Stress Scales, 21 item version (DASS-21) | C10: 4. Psychological distress screening | D10: Free / open access | E10: 21 | F10: =COUNTIF('Master Item List'!$A:$A,$A10) | G10: Three related negative emotional states over the past week: depression (dysphoria, hopelessness, devaluation of life, self deprecation, lack of interest or involvement, anhedonia, inertia), anxiety (autonomic arousal, skeletal muscle effects, situational anxiety, subjective experience of anxious affect) and stress (difficulty relaxing, nervous arousal, being easily upset or agitated, irritable or over reactive, impatient). Built on a dimensional rather than a categorical model of distress. | H10: Self-report | I10: 17+ (NovoPsych); adults and older adolescents | J10: 4 minutes | K10: Public domain. The University of New South Wales DASS site states that the DASS questionnaire is in the public domain and may be downloaded from the site without charge. The form, scoring template and translations are free; only the printed manual is sold (AUD 55). NovoPsych also hosts the DASS-21 with automated scoring and reports for account holders. Charlotte Price Consulting administers it through a Tally form and scores it with the practice DASS-21 report builder. | L10: A brief screening measure to establish whether a client's current distress sits within the range coaching can safely hold, or whether a general practitioner or registered mental health practitioner should be involved before or alongside coaching. Scores describe the past week only, so a repeat administration is needed to separate a difficult week from a developing pattern. It is not a diagnostic instrument and does not assess suicide risk; items 10, 17 and 21 are followed up directly when endorsed at 2 or 3, as the practice report builder does. | M10: The DASS was developed by Lovibond and Lovibond (1995) to measure the three related negative emotional states of depression, anxiety and stress, and to discriminate between them as fully as possible. The 21 item short form takes 7 items from each of the three 14 item scales of the full DASS-42. It is used across clinical, research and non clinical settings to describe current symptom severity and to track change over time, rather than to assign diagnostic categories. | N10: Please read each statement and circle a number 0, 1, 2 or 3 which indicates how much the statement applied to you over the past week. There are no right or wrong answers. Do not spend too much time on any statement. | O10: Did not apply to me at all = 0 | Applied to me to some degree, or some of the time = 1 | Applied to me to a considerable degree, or a good part of time = 2 | Applied to me very much, or most of the time = 3 | P10: None | Q10: None | R10: Depression (items 3, 5, 10, 13, 16-17, 21; n=7; range 0-21 raw; 0-42 after doubling) Anxiety (items 2, 4, 7, 9, 15, 19-20; n=7; range 0-21 raw; 0-42 after doubling) Stress (items 1, 6, 8, 11-12, 14, 18; n=7; range 0-21 raw; 0-42 after doubling) | S10: Each item is rated 0 to 3 for the past week. The 7 items of each subscale are summed (raw range 0 to 21) and the sum is multiplied by 2, placing each subscale on the same 0 to 42 range as the full DASS-42 so that the published severity labels can be applied. No items are reverse scored. A total distress score (sum of all 21 items, doubled) is sometimes reported but the three subscales are the primary outputs. | T10: Depression - Normal: 0-9 - Within the normal range for the general adult population. Depression - Mild: 10-13 - Above the population mean; conventionally labelled mild. Depression - Moderate: 14-20 - Clearly above the normal range; duration is the key clinical question. Depression - Severe: 21-27 - Well above the normal range; clinical involvement is indicated. Depression - Extremely severe: 28-42 - Highest severity band; clinical contact is the first step. Anxiety - Normal: 0-7 - Within the normal range. Anxiety - Mild: 8-9 - Above the population mean. Anxiety - Moderate: 10-14 - Clearly above the normal range. Anxiety - Severe: 15-19 - Well above the normal range; general practitioner review is also useful because several items are physical symptoms. Anxiety - Extremely severe: 20-42 - Highest severity band. Stress - Normal: 0-14 - Within the normal range. Stress - Mild: 15-18 - Above the population mean. Stress - Moderate: 19-25 - Clearly above the normal range; most responsive of the three to workload and structure. Stress - Severe: 26-33 - Well above the normal range; sustained arousal at this level commonly precedes exhaustion. Stress - Extremely severe: 34-42 - Highest severity band. | U10: Severity labels (Lovibond & Lovibond, 1995) applied to the doubled subscale score. Depression: Normal 0-9, Mild 10-13, Moderate 14-20, Severe 21-27, Extremely severe 28+. Anxiety: Normal 0-7, Mild 8-9, Moderate 10-14, Severe 15-19, Extremely severe 20+. Stress: Normal 0-14, Mild 15-18, Moderate 19-25, Severe 26-33, Extremely severe 34+. These are conventional descriptors of position relative to the population distribution (Normal to approximately the 78th percentile, Mild 78th to 87th, Moderate 87th to 95th, Severe 95th to 98th, Extremely severe 98th and above), not diagnostic thresholds. The DASS-21 contains no item on suicidal thinking and does not assess risk. | V10: Henry and Crawford (2005): non clinical UK adult sample, n = 1,794, provided normative data for the DASS-21 and supported use of the three subscales plus a general distress factor. Antony et al. (1998): clinical groups and a community sample comparing the 42 and 21 item versions. The severity labels derive from the Australian normative work reported in the Lovibond and Lovibond (1995) manual. | W10: Internal consistency in the Henry and Crawford (2005) non clinical sample of 1,794 adults: Depression alpha = .88, Anxiety alpha = .82, Stress alpha = .90, total scale alpha = .93. Confirmatory factor analysis supported a quadripartite structure: three correlated specific factors plus a general negative affectivity factor. Antony et al. (1998) found the DASS-21 subscales reproduced the three factor structure of the full DASS in clinical and community samples, with alphas of .94 (Depression), .87 (Anxiety) and .91 (Stress), and the 21 item version showed a cleaner factor structure than the 42 item version. Brown et al. (1997) supported the three factor structure and discriminant validity in clinical samples. | X10: Lovibond, S. H., & Lovibond, P. F. (1995). Manual for the Depression Anxiety Stress Scales (2nd ed.). Sydney: Psychology Foundation of Australia. | Y10: Public domain. The developers state on the official UNSW DASS site that the questionnaire is in the public domain and may be downloaded and used freely; the printed manual is the only priced item. Items reproduced here verbatim from the official DASS-21 form PDF. | Z10: https://www2.psy.unsw.edu.au/dass/
A11: PTQ | B11: Perseverative Thinking Questionnaire | C11: 5. Repetitive negative thinking and self talk | D11: Free / open access | E11: 15 | F11: =COUNTIF('Master Item List'!$A:$A,$A11) | G11: Repetitive negative thinking (RNT), measured as a content-independent process (applies equally to worry, rumination, or any other form of repetitive negative thought about problems), rather than a specific symptom or diagnostic construct. | H11: Adult self-report | I11: Not stated in the source article. Validation samples were adult (internet, non-clinical, clinical, and English-language) populations; no minimum/maximum age is specified in the text retrieved. | J11: Not stated in the source. A brief 15-item self-report measure, typically completed in a few minutes. | K11: No formal licensing or fee-for-use process was found. The hosted PDF (via OxCADAT Resources, a University of Oxford-affiliated trauma/CBT resource site) carries the standard journal notice "© 2010 Elsevier Ltd. All rights reserved." from Journal of Behavior Therapy and Experimental Psychiatry. No explicit blanket grant for commercial or paid-coaching administration was found in the source, but equally no restriction on non-research/practitioner use was stated; the measure is very widely reproduced in open clinical and training materials without visible enforcement. For a paid coaching practice, treat as reasonably low-risk to administer informally with citation, but not as a confirmed formal commercial licence. Licensing note: Free / open access, with a standard journal copyright notice | L11: The PTQ is useful in coaching as a transdiagnostic check on whether a student or early-career client is getting cognitively "stuck" in repetitive negative thinking about study, performance or career worries, independent of the topic they are ruminating on. Its brevity and content-neutral wording make it easy to reuse across sessions to track whether coaching strategies are reducing the repetitive, unproductive quality of the thinking rather than the topic itself. It is a process measure, not a diagnostic or symptom-severity tool, so elevated scores should prompt a coaching conversation about thinking patterns rather than a clinical judgement, and persistent high scores alongside distress should prompt referral consideration. | M11: The PTQ was developed to measure repetitive negative thinking (RNT) as a content-independent process common to worry, rumination and related forms of perseverative thought, rather than measuring a specific content domain (e.g. depressive rumination or anxious worry). It captures three lower-order aspects of RNT: its core repetitive/intrusive characteristics, its perceived unproductiveness, and the degree to which it captures mental capacity. It was designed to be usable across clinical and research contexts where a single content-independent RNT measure is needed. | N11: In this questionnaire, you will be asked to describe how you typically think about negative experiences or problems. Please read the following statements and rate the extent to which they apply to you when you think about negative experiences or problems. | O11: never = 0 | rarely = 1 | sometimes = 2 | often = 3 | almost always = 4 | P11: None | Q11: None | R11: Core Characteristics of Repetitive Negative Thinking (items 1-3, 6-8, 11-13; n=9; range 0-36) Unproductiveness (items 4, 9, 14; n=3; range 0-12) Capturing Mental Capacity (items 5, 10, 15; n=3; range 0-12) | S11: Total PTQ score is the sum of all 15 items (range 0-60), computed as recommended in the source article. Each of the three subscale scores is the sum of its own items (each subscale range 0-36 for Core Characteristics, 0-12 for the other two). | T11: Not stated on source | U11: No clinical cutoff scores or interpretive bands were reported in the source article that was fetched. | V11: No published normative means/SDs by population were reported in the source article beyond describing four validation samples: an internet sample, a German non-clinical sample, a German clinical sample, and an English-language sample, totalling N = 1,832 across Study 1 and Study 2. Exact per-sample means/SDs were not extractable from the fetched text. | W11: Internal consistency: Cronbach's alpha = .95 (Study 1, internet sample), .94 (Study 1, non-clinical sample), .95 (Study 1, clinical sample), .95 (Study 2, English-language sample). Test-retest reliability over a 4-week interval: r = .69, p < .001 (n = 186). (Ehring et al., 2011.) | X11: Ehring, T., Zetsche, U., Weidacker, K., Wahl, K., Schönfeld, S., & Ehlers, A. (2011). The Perseverative Thinking Questionnaire (PTQ): Validation of a content-independent measure of repetitive negative thinking. Journal of Behavior Therapy and Experimental Psychiatry, 42(2), 225–232. https://doi.org/10.1016/j.jbtep.2010.12.003 | Y11: © 2010 Elsevier Ltd. All rights reserved. (Copyright notice appears on the hosted article/PDF; no separate explicit permission statement for reproduction, non-commercial use, or commercial/coaching administration was found in the fetched source.) | Z11: https://oxcadatresources.com/wp-content/uploads/2020/09/EhringetalRuminationQuestionnaire.2011.pdf
A12: RRS | B12: Ruminative Responses Scale | C12: 5. Repetitive negative thinking and self talk | D12: Free / open access | E12: 22 | F12: =COUNTIF('Master Item List'!$A:$A,$A12) | G12: Trait rumination in response to low mood: the tendency to repetitively focus attention on the symptoms and possible causes/consequences of one's depressed mood. The Treynor et al. (2003) refinement splits this into a passive, self-critical/moody-pondering component (Brooding) and a more deliberate, analytic component (Reflection), leaving 12 items that overlap with depressive symptoms unscored in either subscale. | H12: Adult self-report | I12: NovoPsych lists 18 years and older. The original Nolen-Hoeksema & Morrow (1991) and Treynor et al. (2003) sources do not themselves state an age range in the text retrieved. | J12: Approximately 2 minutes (per NovoPsych). | K12: The 22 items and simple summed scoring are freely available from the developer-hosted PDFs (Susan Nolen-Hoeksema's own item sheet, and the Treynor et al. subscale-mapping paper), with no explicit copyright or commercial-use restriction stated on either document. NovoPsych also hosts the RRS with automated scoring, but its scoring/psychometrics detail is gated behind NovoPsych's paid professional-access platform (app.novopsych.com registration required); this session could not retrieve NovoPsych's own cutoff, norm or psychometric text for the RRS specifically (its RRS page did not expose that content, and no NovoPsych-hosted RRS blank-form or sample-results PDF could be located). For manual/paper administration in coaching, the items may be used and hand-scored directly from the developer sources with citation; for automated scoring, reporting and any NovoPsych-specific norms, a NovoPsych subscription would be required. Licensing note: Free / open access for the item content and scoring algorithm (no restriction found in the developer sources); full scoring, norms and psychometrics on the NovoPsych platform sit behind NovoPsych's professional/paid clinician access. | L12: The RRS, and the Brooding subscale in particular, is well suited to coaching conversations with students and early-career clients about unhelpful dwelling on setbacks (e.g. "why can't I handle things better") versus more adaptive, problem-focused reflection. Distinguishing Brooding from Reflection lets Charlotte target the maladaptive pattern directly (as a coaching focus) while validating that some analytic self-reflection is normal and can be constructive. Because 12 of the 22 items closely track depressive symptoms rather than rumination style, the total 22-item score should be interpreted cautiously in a non-clinical coaching context and the Brooding/Reflection subscales are generally the more directly actionable pickup. | M12: The RRS was originally developed by Nolen-Hoeksema and Morrow (1991) to assess ruminative responses to depressed mood as part of the Response Styles Questionnaire. Treynor, Gonzalez and Nolen-Hoeksema (2003) later re-analysed the scale and identified two "pure" 5-item subscales within it, Brooding (passive, self-critical comparison of one's current state to an unachieved standard) and Reflection (deliberate, analytic turning inward to understand one's low mood), while the remaining 12 items were found to overlap substantially with depressive symptoms themselves and are not used in either subscale score. | N12: Please read each of the items below and indicate whether you almost never, sometimes, often, or almost always think or do each one when you feel down, sad, or depressed. Please indicate what you generally do, not what you think you should do. | O12: almost never = 1 | sometimes = 2 | often = 3 | almost always = 4 | P12: None | Q12: None | R12: Brooding (items 5, 10, 13, 15-16; n=5; range 5-20) Reflection (items 7, 11-12, 20-21; n=5; range 5-20) Depression-related items (not scored as a subscale) (items 1-4, 6, 8-9, 14, 17-19, 22; n=12; range 12-48) | S12: Full-scale total: sum of all 22 items (range 22-88), per Nolen-Hoeksema's own scoring note ("simply sum the scores on the 22 items"). Brooding and Reflection subscale scores are each the sum of their 5 items (range 5-20 each), per Treynor et al. (2003). | T12: Not stated on source | U12: No clinical cutoff scores were found in the developer sources (Nolen-Hoeksema & Morrow, 1991; Treynor et al., 2003) or retrievable from the NovoPsych RRS page, which itself does not display specific score ranges or interpretation bands in the content that could be fetched this session. | V12: Treynor et al. (2003) used a community sample of N = 1,130 adults assessed at two time points approximately one year apart, but exact normative means/SDs were not extractable from the fetched text. NovoPsych's own normative data for the RRS could not be retrieved this session (its scoring/psychometrics content did not come through fetch, and no NovoPsych-hosted RRS blank-form or sample-results PDF could be located via search). | W12: Full 22-item scale: Cronbach's alpha = .90 (Time 1); test-retest r = .67 across the ~1-year interval. Brooding subscale: alpha = .77 (Time 1); test-retest r = .62. Reflection subscale: alpha = .72 (Time 1); test-retest r = .60. Sample: N = 1,130 community adults (Treynor, Gonzalez, & Nolen-Hoeksema, 2003). | X12: Nolen-Hoeksema, S., & Morrow, J. (1991). A prospective study of depression and posttraumatic stress symptoms after a natural disaster: The 1989 Loma Prieta earthquake. Journal of Personality and Social Psychology, 61(1), 115–121. https://doi.org/10.1037/0022-3514.61.1.115 | Y12: The Nolen-Hoeksema item PDF carries no explicit copyright/licence statement beyond her name and Yale University letter header in the source fetched; no blanket free-for-commercial-use grant nor an explicit restriction was found in either developer source. NovoPsych's own terms govern use of its platform-hosted administration and scoring, which was not accessible in full this session. | Z12: https://novopsych.com/assessments/formulation/ruminative-responses-scale-rrs/
A13: FSCRS | B13: Forms of Self-Criticising/Attacking and Self-Reassuring Scale | C13: 5. Repetitive negative thinking and self talk | D13: Free / open access | E13: 22 | F13: =COUNTIF('Master Item List'!$A:$A,$A13) | G13: Self-criticism and self-reassurance as distinct forms of self-relating that people use when things go wrong: an inadequacy-focused form of self-criticism, a more punitive, self-disgust-based (hated-self) form of self-criticism, and the capacity to be self-reassuring/self-supportive. | H13: Adult self-report | I13: Not stated on the source document. The original 2004 development sample was female university students; the scale has since been used across adult clinical and non-clinical populations, but no formal age range is specified in the fetched source. | J13: Not stated in the source. A brief 22-item self-report measure, typically completed in a few minutes. | K13: The scale is freely downloadable (e.g. via the Portland Psychotherapy Clinic hosting used here) and is very widely used in clinical, compassion-focused therapy and coaching-adjacent contexts without a reported paywall or licensing fee. The document carries the notice "© Gilbert et al., 2004" but no explicit statement granting or restricting commercial/paid-coaching use. Treat as reasonably safe to administer with citation, but not as a confirmed formal commercial licence; a courtesy email to the authors would close this gap before large-scale paid use. Licensing note: Free / open access, with an author copyright notice | L13: The FSCRS is one of the strongest available tools for identifying harsh, punitive self-talk under academic or early-career performance pressure, and it usefully separates self-criticism (Inadequate Self, Hated Self) from the client's existing capacity to self-reassure (Reassured Self), which is directly actionable as a coaching target. Because item 9 references wanting to hurt or injure oneself, it needs careful, consent-based framing in a non-clinical coaching setting, with a clear plan for what happens if it is endorsed, and should be introduced only once appropriate rapport and safety-checking practices are in place. As a self-report measure of self-relating style rather than a diagnostic tool, elevated Hated Self scores should prompt sensitive follow-up and, where indicated, referral rather than being worked with in coaching alone. | M13: The FSCRS was developed by Gilbert, Clarke, Hempel, Miles and Irons (2004) to explore the different forms, styles and functions of self-criticism and self-reassurance that people use when they feel they have fallen short or things have gone wrong. It distinguishes an inadequacy-focused form of self-attacking from a more hostile, punitive, self-disgust/self-hatred form, and separately measures the person's capacity to respond to setbacks with self-support and self-reassurance. | N13: When things go wrong in our lives or don't work out as we hoped, and we feel we could have done better, we sometimes have negative and self-critical thoughts and feelings. These may take the form of feeling worthless, useless or inferior etc. However, people can also try to be supportive of themselves. Below are a series of thoughts and feelings that people sometimes have. Read each statement carefully and circle the number that best describes how much each statement is true for you. Please use the scale below. | O13: Not at all like me = 0 | A little bit like me = 1 | Moderately like me = 2 | Quite a bit like me = 3 | Extremely like me = 4 | P13: None | Q13: None | R13: Inadequate Self (items 1-2, 4, 6-7, 14, 17-18, 20; n=9; range 0-36) Hated Self (items 9-10, 12, 15, 22; n=5; range 0-20) Reassured Self (items 3, 5, 8, 11, 13, 16, 19, 21; n=8; range 0-32) | S13: Each subscale is scored as the sum of its own items: Inadequate Self (9 items, range 0-36), Hated Self (5 items, range 0-20), Reassured Self (8 items, range 0-32). There is no single overall FSCRS total; the three subscales are interpreted separately (Gilbert et al., 2004). | T13: Not stated on source | U13: No clinical cutoff scores were reported in the fetched source. | V13: No normative means/SDs by population were extractable from the fetched source. The original development sample was female university students (UK); the source notes the scale has since been re-validated across thirteen countries (Baíao et al., 2015 normative study), but that paper was not directly fetched this session. | W13: Cronbach's alpha = .90 (Inadequate Self), .86 (Hated Self), .86 (Reassured Self), as reported in the fetched source document (Gilbert et al., 2004). | X13: Gilbert, P., Clarke, M., Hempel, S., Miles, J. N. V., & Irons, C. (2004). Criticizing and reassuring oneself: An exploration of forms, styles and reasons in female students. British Journal of Clinical Psychology, 43(1), 31–50. https://doi.org/10.1348/014466504772812959 | Y13: © Gilbert et al., 2004 (notice appears on the source document). No explicit commercial-use grant or restriction was found beyond this author copyright notice. | Z13: https://d3n8a8pro7vhmx.cloudfront.net/portlandpsychotherapy/pages/21/attachments/original/1438799410/Forms_of_self-criticising_and_self_reassuring_scale.pdf
... A21: GADJ | B21: Goal Adjustment Scale | C21: 6. Motivation, self determination and goal pursuit | D21: Free for research; permission needed for commercial use | E21: 10 | F21: =COUNTIF('Master Item List'!$A:$A,$A21) | G21: Adaptive self-regulation in the face of unattainable goals, comprising two related capacities: Goal Disengagement (the ability to withdraw effort and commitment from a goal that can no longer be reached) and Goal Reengagement (the ability to identify, commit to, and pursue new goals after disengaging from an old one). | H21: Self-report, answered with respect to a general stem about an important, unattainable goal in the respondent's own life (not a goal supplied by an interviewer). | I21: Validated across three studies spanning young adulthood to old age: Study 1, undergraduates aged 17-23 (M = 19.35, SD = 1.08); Study 2, young adults aged 19-35 (M = 22.47) and older adults aged 55-89 (M = 69.67); Study 3, parents in their mid-30s to mid-40s (M around 36.9-37.6). No dedicated adolescent (under 17) validation was located. | J21: Not stated on source | K21: No purchase or licence fee is required to view the 10 items; they are reproduced in Table 1 of the original journal article, re-hosted at https://www.cmu.edu/dietrich/psychology/pdf/scales/GAS_article.pdf (fetched and confirmed in this session; this is the original 2003 Personality and Social Psychology Bulletin article, carrying the line "\u00a9 2003 by the Society for Personality and Social Psychology, Inc."). Carnegie Mellon's psychology department also hosts what its filename indicates is a standalone scale-only document at https://www.cmu.edu/dietrich/psychology/pdf/scales/GAS_scale.pdf; this URL was fetched in this session but returned no machine-readable text ("This PDF is empty or contains no machine-readable text"), so it could not be used to confirm a separate administration-ready form, and its existence as a genuinely standalone form is unconfirmed. No copyright, licence, or commercial-use statement appears anywhere in the original article itself. A third-party aggregator, Psychology Roots (https://psychologyroots.com/goal-adjustment-scale/, fetched and quoted directly in this session), states: "Psychology Roots does not have the right to grant permission for the use of any psychological scales or assessments listed on its website. To use any scale or assessment, you must obtain permission directly from the author or translator of the tool," naming the original authors (Wrosch, Scheier, Miller, Schulz, Carver) as the people to contact. Recommend written permission from Carsten Wrosch or Michael F. Scheier before using the GAS as a scored instrument in a commercial coaching product. Licensing detail: Free to view via a university-hosted copy of the original journal article; commercial/paid use is not explicitly addressed by the original authors or publisher, and a third-party scale-listing site states that permission must be obtained directly from the authors | L21: The Goal Adjustment Scale is directly useful in goal-setting coaching with university students and early-career professionals when the presenting issue is a stalled, blocked, or no-longer-realistic goal, such as a failed course, a missed graduate-entry pathway, or a career plan overtaken by events, because it separates the client's capacity to let go of that goal from their capacity to reinvest energy in a new one. Its main limits for this population are that it was validated primarily on undergraduates, community adults, and parents of ill children rather than on a coaching-specific sample, and that a low Reengagement score in a young client may reflect a genuinely open-ended transitional life stage rather than a self-regulatory deficit, so scores should inform conversation rather than be treated as a fixed trait diagnosis. | M21: The Goal Adjustment Scale was developed by Wrosch, Scheier, Miller, Schulz and Carver (2003) to measure two theoretically distinct components of adaptive self-regulation when a personal goal becomes unattainable: disengaging from the blocked goal, and reengaging with new, attainable goals. The scale was validated across three studies (university students, a community sample of young and older adults, and parents of children with or without cancer) and used to test whether disengagement and reengagement independently predict subjective well-being and physical health symptoms. | N21: "If I have to stop pursuing an important goal in my life . . ." This is the generic item stem used for all 10 items in Study 2 and Study 3, quoted verbatim from a footnote to Table 1 of Wrosch et al. (2003), fetched and confirmed in this session. In Study 1, the goal disengagement items only were instead presented against three separate situational stems, one of which is quoted verbatim in the article as: "If it becomes likely that I have to stop pursuing an important goal because I no longer have the opportunity to realize it . . ." | O21: Almost never true = 1 | 2 = 2 | 3 = 3 | 4 = 4 | Almost always true = 5 | P21: 2-3 | Q21: None | R21: Goal Disengagement (items 1-4; n=4; range 4-20 (sum) or 1-5 (mean)) Goal Reengagement (items 5-10; n=6; range 6-30 (sum) or 1-5 (mean)) | S21: Score the two subscales separately; the instrument does not sum to a single overall score. For Goal Disengagement, reverse-score items 2 and 3, then average (or sum) all 4 items; higher scores indicate greater ability to disengage from an unattainable goal. For Goal Reengagement, average (or sum) all 6 items with no reversal; higher scores indicate greater capacity to reengage with new goals. | T21: Not stated on source | U21: Not stated on source | V21: Not stated on source | W21: Cronbach's alpha values quoted verbatim from Wrosch et al. (2003), fetched and confirmed in this session: Study 1 (N = 115 undergraduates), Goal Disengagement α = .84, Goal Reengagement α = .86; Study 2 (N = 120 community adults), Goal Disengagement α = .76, Goal Reengagement α = .89; Study 3 (N = 45 parents), Goal Disengagement α = .79, Goal Reengagement α = .86. Note that a third-party aggregator page (Psychology Roots) states the Study 1 figures (.84 disengagement / .86 reengagement) as if they were the scale's single reliability figures and separately describes the response scale as "1 (Strongly Disagree) to 5 (Strongly Agree)," which conflicts with the "almost never true" to "almost always true" anchors confirmed directly from the primary article's Table 1 footnote; the primary-source anchors are used in this record and the aggregator's anchor wording should be treated as an error. | X21: Wrosch, C., Scheier, M. F., Miller, G. E., Schulz, R., & Carver, C. S. (2003). Adaptive self-regulation of unattainable goals: Goal disengagement, goal reengagement, and subjective well-being. Personality and Social Psychology Bulletin, 29(12), 1494-1508. | Y21: The original article carries the line "\u00a9 2003 by the Society for Personality and Social Psychology, Inc." but no explicit statement about permission to reproduce or use the scale for research, clinical, or commercial purposes appears anywhere in the fetched text. Psychology Roots (third-party aggregator, quoted verbatim above) states that permission must be sought directly from the original authors and that the aggregator itself has no right to grant use permission. | Z21: https://www.cmu.edu/dietrich/psychology/pdf/scales/GAS_article.pdf

Sheet Master Item List
A1: Code | B1: Instrument Name | C1: Domain | D1: Item Number | E1: Item Text (verbatim) | F1: Subscale / Domain | G1: Reverse Scored | H1: Filler (not scored) | I1: Response Options | J1: Item Notes | K1: Source URL
A2: ESQ-R | B2: Executive Skills Questionnaire - Revised (ESQ-R) | C2: 1. Executive functioning and ADHD | D2: 1 | E2: I act on impulse. | F2: Behavioral Regulation | G2: FALSE | H2: FALSE | I2: Never or rarely = 0 | Sometimes = 1 | Often = 2 | Very often = 3 | K2: https://novopsych.com/assessments/formulation/executive-skills-questionnaire-revised-esq-r/
A3: ESQ-R | B3: Executive Skills Questionnaire - Revised (ESQ-R) | C3: 1. Executive functioning and ADHD | D3: 2 | E3: I say things without thinking. | F3: Behavioral Regulation | G3: FALSE | H3: FALSE | I3: Never or rarely = 0 | Sometimes = 1 | Often = 2 | Very often = 3 | K3: https://novopsych.com/assessments/formulation/executive-skills-questionnaire-revised-esq-r/
A4: ESQ-R | B4: Executive Skills Questionnaire - Revised (ESQ-R) | C4: 1. Executive functioning and ADHD | D4: 3 | E4: I lose things. | F4: Organization | G4: FALSE | H4: FALSE | I4: Never or rarely = 0 | Sometimes = 1 | Often = 2 | Very often = 3 | K4: https://novopsych.com/assessments/formulation/executive-skills-questionnaire-revised-esq-r/
A5: ESQ-R | B5: Executive Skills Questionnaire - Revised (ESQ-R) | C5: 1. Executive functioning and ADHD | D5: 4 | E5: I have a short fuse. | F5: Emotional Regulation | G5: FALSE | H5: FALSE | I5: Never or rarely = 0 | Sometimes = 1 | Often = 2 | Very often = 3 | K5: https://novopsych.com/assessments/formulation/executive-skills-questionnaire-revised-esq-r/
A6: ESQ-R | B6: Executive Skills Questionnaire - Revised (ESQ-R) | C6: 1. Executive functioning and ADHD | D6: 5 | E6: I get upset when things don't go as planned. | F6: Emotional Regulation | G6: FALSE | H6: FALSE | I6: Never or rarely = 0 | Sometimes = 1 | Often = 2 | Very often = 3 | K6: https://novopsych.com/assessments/formulation/executive-skills-questionnaire-revised-esq-r/
A7: ESQ-R | B7: Executive Skills Questionnaire - Revised (ESQ-R) | C7: 1. Executive functioning and ADHD | D7: 6 | E7: I run out of steam before finishing a task. | F7: Plan Management | G7: FALSE | H7: FALSE | I7: Never or rarely = 0 | Sometimes = 1 | Often = 2 | Very often = 3 | K7: https://novopsych.com/assessments/formulation/executive-skills-questionnaire-revised-esq-r/
A8: ESQ-R | B8: Executive Skills Questionnaire - Revised (ESQ-R) | C8: 1. Executive functioning and ADHD | D8: 7 | E8: It's hard for me to set priorities when I have a lot of things to do. | F8: Plan Management | G8: FALSE | H8: FALSE | I8: Never or rarely = 0 | Sometimes = 1 | Often = 2 | Very often = 3 | K8: https://novopsych.com/assessments/formulation/executive-skills-questionnaire-revised-esq-r/
A9: ESQ-R | B9: Executive Skills Questionnaire - Revised (ESQ-R) | C9: 1. Executive functioning and ADHD | D9: 8 | E9: My desk or workspace is a mess. | F9: Organization | G9: FALSE | H9: FALSE | I9: Never or rarely = 0 | Sometimes = 1 | Often = 2 | Very often = 3 | K9: https://novopsych.com/assessments/formulation/executive-skills-questionnaire-revised-esq-r/
A10: ESQ-R | B10: Executive Skills Questionnaire - Revised (ESQ-R) | C10: 1. Executive functioning and ADHD | D10: 9 | E10: I have trouble keeping my house or room clean. | F10: Organization | G10: FALSE | H10: FALSE | I10: Never or rarely = 0 | Sometimes = 1 | Often = 2 | Very often = 3 | K10: https://novopsych.com/assessments/formulation/executive-skills-questionnaire-revised-esq-r/
A11: ESQ-R | B11: Executive Skills Questionnaire - Revised (ESQ-R) | C11: 1. Executive functioning and ADHD | D11: 10 | E11: I have trouble estimating how long it will take to complete a task. | F11: Time Management | G11: FALSE | H11: FALSE | I11: Never or rarely = 0 | Sometimes = 1 | Often = 2 | Very often = 3 | K11: https://novopsych.com/assessments/formulation/executive-skills-questionnaire-revised-esq-r/
A12: ESQ-R | B12: Executive Skills Questionnaire - Revised (ESQ-R) | C12: 1. Executive functioning and ADHD | D12: 11 | E12: I'm slow at getting ready for school, work, or appointments. | F12: Time Management | G12: FALSE | H12: FALSE | I12: Never or rarely = 0 | Sometimes = 1 | Often = 2 | Very often = 3 | K12: https://novopsych.com/assessments/formulation/executive-skills-questionnaire-revised-esq-r/
A13: ESQ-R | B13: Executive Skills Questionnaire - Revised (ESQ-R) | C13: 1. Executive functioning and ADHD | D13: 12 | E13: If the first solution to a problem doesn't work, I have trouble thinking of a different one. | F13: Plan Management | G13: FALSE | H13: FALSE | I13: Never or rarely = 0 | Sometimes = 1 | Often = 2 | Very often = 3 | K13: https://novopsych.com/assessments/formulation/executive-skills-questionnaire-revised-esq-r/
... A64: ASRS | B64: Adult ADHD Self-Report Scale (ASRS v1.1) | C64: 1. Executive functioning and ADHD | D64: 18 | E64: How often do you interrupt others when they are busy? | F64: Part B | Hyperactivity/Impulsivity - Verbal | G64: FALSE | H64: FALSE | I64: Never = 0 | Rarely = 1 | Sometimes = 2 | Often = 3 | Very Often = 4 | K64: https://novopsych.com/assessments/diagnosis/adult-adhd-self-report-scale-asrs/
A65: SKS | B65: Strengths Knowledge Scale | C65: 2. Strengths knowledge, use and support at work | D65: 1 | E65: Other people see the strengths that I have | F65: Strengths Knowledge (total scale) | G65: FALSE | H65: FALSE | I65: Strongly disagree = 1 | 2 = 2 | 3 = 3 | 4 = 4 | 5 = 5 | 6 = 6 | Strongly agree = 7 | J65: Verbatim as reproduced in Frontiers in Psychology (2023), Table 5, citing Govindji & Linley (2007). | K65: https://www.frontiersin.org/journals/psychology/articles/10.3389/fpsyg.2023.1086510/full
A66: SKS | B66: Strengths Knowledge Scale | C66: 2. Strengths knowledge, use and support at work | D66: 2 | E66: I have to think hard about what my strengths are | F66: Strengths Knowledge (total scale) | G66: FALSE | H66: FALSE | I66: Strongly disagree = 1 | 2 = 2 | 3 = 3 | 4 = 4 | 5 = 5 | 6 = 6 | Strongly agree = 7 | J66: Verbatim as reproduced in Frontiers in Psychology (2023), Table 5. One secondary aggregator source (db.arabpsychology.com) describes this item as reverse-scored, but the Frontiers (2023) reproduction directly consulted for this record states no reverse-scored items are present for either scale, so reverse scoring for this item could not be independently confirmed and is left unmarked pending sight of the original 2007 scoring key. | K66: https://www.frontiersin.org/journals/psychology/articles/10.3389/fpsyg.2023.1086510/full
A67: SKS | B67: Strengths Knowledge Scale | C67: 2. Strengths knowledge, use and support at work | D67: 3 | E67: I know what I do best | F67: Strengths Knowledge (total scale) | G67: FALSE | H67: FALSE | I67: Strongly disagree = 1 | 2 = 2 | 3 = 3 | 4 = 4 | 5 = 5 | 6 = 6 | Strongly agree = 7 | J67: Verbatim as reproduced in Frontiers in Psychology (2023), Table 5. | K67: https://www.frontiersin.org/journals/psychology/articles/10.3389/fpsyg.2023.1086510/full
A68: SKS | B68: Strengths Knowledge Scale | C68: 2. Strengths knowledge, use and support at work | D68: 4 | E68: I am aware of my strengths | F68: Strengths Knowledge (total scale) | G68: FALSE | H68: FALSE | I68: Strongly disagree = 1 | 2 = 2 | 3 = 3 | 4 = 4 | 5 = 5 | 6 = 6 | Strongly agree = 7 | J68: Verbatim as reproduced in Frontiers in Psychology (2023), Table 5. | K68: https://www.frontiersin.org/journals/psychology/articles/10.3389/fpsyg.2023.1086510/full
A69: SKS | B69: Strengths Knowledge Scale | C69: 2. Strengths knowledge, use and support at work | D69: 5 | E69: I know the things I am good at doing | F69: Strengths Knowledge (total scale) | G69: FALSE | H69: FALSE | I69: Strongly disagree = 1 | 2 = 2 | 3 = 3 | 4 = 4 | 5 = 5 | 6 = 6 | Strongly agree = 7 | J69: Verbatim as reproduced in Frontiers in Psychology (2023), Table 5. | K69: https://www.frontiersin.org/journals/psychology/articles/10.3389/fpsyg.2023.1086510/full
A70: SKS | B70: Strengths Knowledge Scale | C70: 2. Strengths knowledge, use and support at work | D70: 6 | E70: I know my strengths well | F70: Strengths Knowledge (total scale) | G70: FALSE | H70: FALSE | I70: Strongly disagree = 1 | 2 = 2 | 3 = 3 | 4 = 4 | 5 = 5 | 6 = 6 | Strongly agree = 7 | J70: Verbatim as reproduced in Frontiers in Psychology (2023), Table 5. | K70: https://www.frontiersin.org/journals/psychology/articles/10.3389/fpsyg.2023.1086510/full
A71: SKS | B71: Strengths Knowledge Scale | C71: 2. Strengths knowledge, use and support at work | D71: 7 | E71: I know the things I do best | F71: Strengths Knowledge (total scale) | G71: FALSE | H71: FALSE | I71: Strongly disagree = 1 | 2 = 2 | 3 = 3 | 4 = 4 | 5 = 5 | 6 = 6 | Strongly agree = 7 | J71: Verbatim as reproduced in Frontiers in Psychology (2023), Table 5. | K71: https://www.frontiersin.org/journals/psychology/articles/10.3389/fpsyg.2023.1086510/full
A72: SKS | B72: Strengths Knowledge Scale | C72: 2. Strengths knowledge, use and support at work | D72: 8 | E72: I know when I am at my best | F72: Strengths Knowledge (total scale) | G72: FALSE | H72: FALSE | I72: Strongly disagree = 1 | 2 = 2 | 3 = 3 | 4 = 4 | 5 = 5 | 6 = 6 | Strongly agree = 7 | J72: Verbatim as reproduced in Frontiers in Psychology (2023), Table 5. | K72: https://www.frontiersin.org/journals/psychology/articles/10.3389/fpsyg.2023.1086510/full
A73: SUS | B73: Strengths Use Scale | C73: 2. Strengths knowledge, use and support at work | D73: 1 | E73: I am regularly able to do what I do best. | F73: Strengths Use (total scale) | G73: FALSE | H73: FALSE | I73: Strongly disagree = 1 | 2 = 2 | 3 = 3 | 4 = 4 | 5 = 5 | 6 = 6 | Strongly agree = 7 | J73: Verbatim as reproduced in Frontiers in Psychology (2023), Table 2, citing Govindji & Linley (2007). | K73: https://www.frontiersin.org/journals/psychology/articles/10.3389/fpsyg.2023.1086510/full
A74: SUS | B74: Strengths Use Scale | C74: 2. Strengths knowledge, use and support at work | D74: 2 | E74: I always play to my strengths. | F74: Strengths Use (total scale) | G74: FALSE | H74: FALSE | I74: Strongly disagree = 1 | 2 = 2 | 3 = 3 | 4 = 4 | 5 = 5 | 6 = 6 | Strongly agree = 7 | J74: Verbatim as reproduced in Frontiers in Psychology (2023), Table 2. | K74: https://www.frontiersin.org/journals/psychology/articles/10.3389/fpsyg.2023.1086510/full
A75: SUS | B75: Strengths Use Scale | C75: 2. Strengths knowledge, use and support at work | D75: 3 | E75: I always try to use my strengths. | F75: Strengths Use (total scale) | G75: FALSE | H75: FALSE | I75: Strongly disagree = 1 | 2 = 2 | 3 = 3 | 4 = 4 | 5 = 5 | 6 = 6 | Strongly agree = 7 | J75: Verbatim as reproduced in Frontiers in Psychology (2023), Table 2. | K75: https://www.frontiersin.org/journals/psychology/articles/10.3389/fpsyg.2023.1086510/full
A76: SUS | B76: Strengths Use Scale | C76: 2. Strengths knowledge, use and support at work | D76: 4 | E76: I achieve what I want by using my strengths. | F76: Strengths Use (total scale) | G76: FALSE | H76: FALSE | I76: Strongly disagree = 1 | 2 = 2 | 3 = 3 | 4 = 4 | 5 = 5 | 6 = 6 | Strongly agree = 7 | J76: Verbatim as reproduced in Frontiers in Psychology (2023), Table 2. | K76: https://www.frontiersin.org/journals/psychology/articles/10.3389/fpsyg.2023.1086510/full
... A97: SSES | B97: Strengths Self-Efficacy Scale | C97: 2. Strengths knowledge, use and support at work | D97: 11 | E97: Practice your strengths in areas where you excel? | F97: Strengths Self-Efficacy (total scale) | G97: FALSE | H97: FALSE | I97: Not confident at all = 1 | 2 = 2 | 3 = 3 | 4 = 4 | Moderately confident = 5 | 6 = 6 | 7 = 7 | 8 = 8 | 9 = 9 | Extremely confident = 10 | J97: Verbatim as reproduced in the PositivePsychology.com PDF, corroborated by academia.edu reproduction. | K97: https://positivepsychology.com/wp-content/uploads/The-Strengths-Self-efficacy-Scale.pdf
A98: CSES | B98: Core Self-Evaluations Scale | C98: 3. Adjacent occupational and wellbeing | D98: 1 | E98: I am confident I get the success I deserve in life. | F98: Core Self-Evaluations (total scale, unidimensional) | G98: FALSE | H98: FALSE | I98: Strongly Disagree = 1 | Disagree = 2 | Neutral = 3 | Agree = 4 | Strongly Agree = 5 | K98: http://ionilies.com/SIOP03/Files/CSES.pdf
A99: CSES | B99: Core Self-Evaluations Scale | C99: 3. Adjacent occupational and wellbeing | D99: 2 | E99: Sometimes I feel depressed. | F99: Core Self-Evaluations (total scale, unidimensional) | G99: TRUE | H99: FALSE | I99: Strongly Disagree = 1 | Disagree = 2 | Neutral = 3 | Agree = 4 | Strongly Agree = 5 | J99: Touches on depressed mood; use sensitively with clients where wellbeing is a live concern. | K99: http://ionilies.com/SIOP03/Files/CSES.pdf
A100: CSES | B100: Core Self-Evaluations Scale | C100: 3. Adjacent occupational and wellbeing | D100: 3 | E100: When I try, I generally succeed. | F100: Core Self-Evaluations (total scale, unidimensional) | G100: FALSE | H100: FALSE | I100: Strongly Disagree = 1 | Disagree = 2 | Neutral = 3 | Agree = 4 | Strongly Agree = 5 | K100: http://ionilies.com/SIOP03/Files/CSES.pdf
A101: CSES | B101: Core Self-Evaluations Scale | C101: 3. Adjacent occupational and wellbeing | D101: 4 | E101: Sometimes when I fail I feel worthless. | F101: Core Self-Evaluations (total scale, unidimensional) | G101: TRUE | H101: FALSE | I101: Strongly Disagree = 1 | Disagree = 2 | Neutral = 3 | Agree = 4 | Strongly Agree = 5 | K101: http://ionilies.com/SIOP03/Files/CSES.pdf
A102: CSES | B102: Core Self-Evaluations Scale | C102: 3. Adjacent occupational and wellbeing | D102: 5 | E102: I complete tasks successfully. | F102: Core Self-Evaluations (total scale, unidimensional) | G102: FALSE | H102: FALSE | I102: Strongly Disagree = 1 | Disagree = 2 | Neutral = 3 | Agree = 4 | Strongly Agree = 5 | K102: http://ionilies.com/SIOP03/Files/CSES.pdf
A103: CSES | B103: Core Self-Evaluations Scale | C103: 3. Adjacent occupational and wellbeing | D103: 6 | E103: Sometimes, I do not feel in control of my work. | F103: Core Self-Evaluations (total scale, unidimensional) | G103: TRUE | H103: FALSE | I103: Strongly Disagree = 1 | Disagree = 2 | Neutral = 3 | Agree = 4 | Strongly Agree = 5 | K103: http://ionilies.com/SIOP03/Files/CSES.pdf
A104: CSES | B104: Core Self-Evaluations Scale | C104: 3. Adjacent occupational and wellbeing | D104: 7 | E104: Overall, I am satisfied with myself. | F104: Core Self-Evaluations (total scale, unidimensional) | G104: FALSE | H104: FALSE | I104: Strongly Disagree = 1 | Disagree = 2 | Neutral = 3 | Agree = 4 | Strongly Agree = 5 | K104: http://ionilies.com/SIOP03/Files/CSES.pdf
A105: CSES | B105: Core Self-Evaluations Scale | C105: 3. Adjacent occupational and wellbeing | D105: 8 | E105: I am filled with doubts about my competence. | F105: Core Self-Evaluations (total scale, unidimensional) | G105: TRUE | H105: FALSE | I105: Strongly Disagree = 1 | Disagree = 2 | Neutral = 3 | Agree = 4 | Strongly Agree = 5 | K105: http://ionilies.com/SIOP03/Files/CSES.pdf
A106: CSES | B106: Core Self-Evaluations Scale | C106: 3. Adjacent occupational and wellbeing | D106: 9 | E106: I determine what will happen in my life. | F106: Core Self-Evaluations (total scale, unidimensional) | G106: FALSE | H106: FALSE | I106: Strongly Disagree = 1 | Disagree = 2 | Neutral = 3 | Agree = 4 | Strongly Agree = 5 | K106: http://ionilies.com/SIOP03/Files/CSES.pdf
A107: CSES | B107: Core Self-Evaluations Scale | C107: 3. Adjacent occupational and wellbeing | D107: 10 | E107: I do not feel in control of my success in my career. | F107: Core Self-Evaluations (total scale, unidimensional) | G107: TRUE | H107: FALSE | I107: Strongly Disagree = 1 | Disagree = 2 | Neutral = 3 | Agree = 4 | Strongly Agree = 5 | K107: http://ionilies.com/SIOP03/Files/CSES.pdf
A108: CSES | B108: Core Self-Evaluations Scale | C108: 3. Adjacent occupational and wellbeing | D108: 11 | E108: I am capable of coping with most of my problems. | F108: Core Self-Evaluations (total scale, unidimensional) | G108: FALSE | H108: FALSE | I108: Strongly Disagree = 1 | Disagree = 2 | Neutral = 3 | Agree = 4 | Strongly Agree = 5 | K108: http://ionilies.com/SIOP03/Files/CSES.pdf
A109: CSES | B109: Core Self-Evaluations Scale | C109: 3. Adjacent occupational and wellbeing | D109: 12 | E109: There are times when things look pretty bleak and hopeless to me. | F109: Core Self-Evaluations (total scale, unidimensional) | G109: TRUE | H109: FALSE | I109: Strongly Disagree = 1 | Disagree = 2 | Neutral = 3 | Agree = 4 | Strongly Agree = 5 | J109: Touches on hopelessness; use sensitively with clients where wellbeing is a live concern. | K109: http://ionilies.com/SIOP03/Files/CSES.pdf
A110: PES | B110: Psychological Empowerment Scale | C110: 3. Adjacent occupational and wellbeing | D110: 1 | E110: The work that I do is important to me. | F110: Meaning | G110: FALSE | H110: FALSE | I110: Very Strongly Disagree = 1 | Strongly Disagree = 2 | Disagree = 3 | Neutral = 4 | Agree = 5 | Strongly Agree = 6 | Very Strongly Agree = 7 | K110: https://webuser.bus.umich.edu/spreitze/Pdfs/EmpowerInstrument.pdf
A111: PES | B111: Psychological Empowerment Scale | C111: 3. Adjacent occupational and wellbeing | D111: 2 | E111: My job activities are personally meaningful to me. | F111: Meaning | G111: FALSE | H111: FALSE | I111: Very Strongly Disagree = 1 | Strongly Disagree = 2 | Disagree = 3 | Neutral = 4 | Agree = 5 | Strongly Agree = 6 | Very Strongly Agree = 7 | K111: https://webuser.bus.umich.edu/spreitze/Pdfs/EmpowerInstrument.pdf
A112: PES | B112: Psychological Empowerment Scale | C112: 3. Adjacent occupational and wellbeing | D112: 3 | E112: The work I do is meaningful to me. | F112: Meaning | G112: FALSE | H112: FALSE | I112: Very Strongly Disagree = 1 | Strongly Disagree = 2 | Disagree = 3 | Neutral = 4 | Agree = 5 | Strongly Agree = 6 | Very Strongly Agree = 7 | K112: https://webuser.bus.umich.edu/spreitze/Pdfs/EmpowerInstrument.pdf
A113: PES | B113: Psychological Empowerment Scale | C113: 3. Adjacent occupational and wellbeing | D113: 4 | E113: I am confident about my ability to do my job. | F113: Competence | G113: FALSE | H113: FALSE | I113: Very Strongly Disagree = 1 | Strongly Disagree = 2 | Disagree = 3 | Neutral = 4 | Agree = 5 | Strongly Agree = 6 | Very Strongly Agree = 7 | K113: https://webuser.bus.umich.edu/spreitze/Pdfs/EmpowerInstrument.pdf
A114: PES | B114: Psychological Empowerment Scale | C114: 3. Adjacent occupational and wellbeing | D114: 5 | E114: I have mastered the skills necessary for my job. | F114: Competence | G114: FALSE | H114: FALSE | I114: Very Strongly Disagree = 1 | Strongly Disagree = 2 | Disagree = 3 | Neutral = 4 | Agree = 5 | Strongly Agree = 6 | Very Strongly Agree = 7 | K114: https://webuser.bus.umich.edu/spreitze/Pdfs/EmpowerInstrument.pdf
A115: PES | B115: Psychological Empowerment Scale | C115: 3. Adjacent occupational and wellbeing | D115: 6 | E115: I am self-assured about my capabilities to perform my work activities. | F115: Competence | G115: FALSE | H115: FALSE | I115: Very Strongly Disagree = 1 | Strongly Disagree = 2 | Disagree = 3 | Neutral = 4 | Agree = 5 | Strongly Agree = 6 | Very Strongly Agree = 7 | K115: https://webuser.bus.umich.edu/spreitze/Pdfs/EmpowerInstrument.pdf
A116: PES | B116: Psychological Empowerment Scale | C116: 3. Adjacent occupational and wellbeing | D116: 7 | E116: I have significant autonomy in determining how I do my job. | F116: Self-Determination | G116: FALSE | H116: FALSE | I116: Very Strongly Disagree = 1 | Strongly Disagree = 2 | Disagree = 3 | Neutral = 4 | Agree = 5 | Strongly Agree = 6 | Very Strongly Agree = 7 | K116: https://webuser.bus.umich.edu/spreitze/Pdfs/EmpowerInstrument.pdf
A117: PES | B117: Psychological Empowerment Scale | C117: 3. Adjacent occupational and wellbeing | D117: 8 | E117: I can decide on my own how to go about doing my own work. | F117: Self-Determination | G117: FALSE | H117: FALSE | I117: Very Strongly Disagree = 1 | Strongly Disagree = 2 | Disagree = 3 | Neutral = 4 | Agree = 5 | Strongly Agree = 6 | Very Strongly Agree = 7 | K117: https://webuser.bus.umich.edu/spreitze/Pdfs/EmpowerInstrument.pdf
A118: PES | B118: Psychological Empowerment Scale | C118: 3. Adjacent occupational and wellbeing | D118: 9 | E118: I have considerable opportunity for independence and freedom in how I do my job. | F118: Self-Determination | G118: FALSE | H118: FALSE | I118: Very Strongly Disagree = 1 | Strongly Disagree = 2 | Disagree = 3 | Neutral = 4 | Agree = 5 | Strongly Agree = 6 | Very Strongly Agree = 7 | K118: https://webuser.bus.umich.edu/spreitze/Pdfs/EmpowerInstrument.pdf
A119: PES | B119: Psychological Empowerment Scale | C119: 3. Adjacent occupational and wellbeing | D119: 10 | E119: My impact on what happens in my department is large. | F119: Impact | G119: FALSE | H119: FALSE | I119: Very Strongly Disagree = 1 | Strongly Disagree = 2 | Disagree = 3 | Neutral = 4 | Agree = 5 | Strongly Agree = 6 | Very Strongly Agree = 7 | K119: https://webuser.bus.umich.edu/spreitze/Pdfs/EmpowerInstrument.pdf
A120: PES | B120: Psychological Empowerment Scale | C120: 3. Adjacent occupational and wellbeing | D120: 11 | E120: I have a great deal of control over what happens in my department. | F120: Impact | G120: FALSE | H120: FALSE | I120: Very Strongly Disagree = 1 | Strongly Disagree = 2 | Disagree = 3 | Neutral = 4 | Agree = 5 | Strongly Agree = 6 | Very Strongly Agree = 7 | K120: https://webuser.bus.umich.edu/spreitze/Pdfs/EmpowerInstrument.pdf
A121: PES | B121: Psychological Empowerment Scale | C121: 3. Adjacent occupational and wellbeing | D121: 12 | E121: I have significant influence over what happens in my department. | F121: Impact | G121: FALSE | H121: FALSE | I121: Very Strongly Disagree = 1 | Strongly Disagree = 2 | Disagree = 3 | Neutral = 4 | Agree = 5 | Strongly Agree = 6 | Very Strongly Agree = 7 | K121: https://webuser.bus.umich.edu/spreitze/Pdfs/EmpowerInstrument.pdf
... A130: DASS-21 | B130: Depression Anxiety Stress Scales, 21 item version (DASS-21) | C130: 4. Psychological distress screening | D130: 9 | E130: I was worried about situations in which I might panic and make a fool of myself | F130: Anxiety | G130: FALSE | H130: FALSE | I130: Did not apply to me at all = 0 | Applied to me to some degree, or some of the time = 1 | Applied to me to a considerable degree, or a good part of time = 2 | Applied to me very much, or most of the time = 3 | K130: https://www2.psy.unsw.edu.au/dass/
A131: DASS-21 | B131: Depression Anxiety Stress Scales, 21 item version (DASS-21) | C131: 4. Psychological distress screening | D131: 10 | E131: I felt that I had nothing to look forward to | F131: Depression | G131: FALSE | H131: FALSE | I131: Did not apply to me at all = 0 | Applied to me to some degree, or some of the time = 1 | Applied to me to a considerable degree, or a good part of time = 2 | Applied to me very much, or most of the time = 3 | J131: Followed up directly when endorsed at 2 or 3 (practice protocol). | K131: https://www2.psy.unsw.edu.au/dass/
A132: DASS-21 | B132: Depression Anxiety Stress Scales, 21 item version (DASS-21) | C132: 4. Psychological distress screening | D132: 11 | E132: I found myself getting agitated | F132: Stress | G132: FALSE | H132: FALSE | I132: Did not apply to me at all = 0 | Applied to me to some degree, or some of the time = 1 | Applied to me to a considerable degree, or a good part of time = 2 | Applied to me very much, or most of the time = 3 | K132: https://www2.psy.unsw.edu.au/dass/
A133: DASS-21 | B133: Depression Anxiety Stress Scales, 21 item version (DASS-21) | C133: 4. Psychological distress screening | D133: 12 | E133: I found it difficult to relax | F133: Stress | G133: FALSE | H133: FALSE | I133: Did not apply to me at all = 0 | Applied to me to some degree, or some of the time = 1 | Applied to me to a considerable degree, or a good part of time = 2 | Applied to me very much, or most of the time = 3 | K133: https://www2.psy.unsw.edu.au/dass/
A134: DASS-21 | B134: Depression Anxiety Stress Scales, 21 item version (DASS-21) | C134: 4. Psychological distress screening | D134: 13 | E134: I felt down-hearted and blue | F134: Depression | G134: FALSE | H134: FALSE | I134: Did not apply to me at all = 0 | Applied to me to some degree, or some of the time = 1 | Applied to me to a considerable degree, or a good part of time = 2 | Applied to me very much, or most of the time = 3 | K134: https://www2.psy.unsw.edu.au/dass/
A135: DASS-21 | B135: Depression Anxiety Stress Scales, 21 item version (DASS-21) | C135: 4. Psychological distress screening | D135: 14 | E135: I was intolerant of anything that kept me from getting on with what I was doing | F135: Stress | G135: FALSE | H135: FALSE | I135: Did not apply to me at all = 0 | Applied to me to some degree, or some of the time = 1 | Applied to me to a considerable degree, or a good part of time = 2 | Applied to me very much, or most of the time = 3 | K135: https://www2.psy.unsw.edu.au/dass/
A136: DASS-21 | B136: Depression Anxiety Stress Scales, 21 item version (DASS-21) | C136: 4. Psychological distress screening | D136: 15 | E136: I felt I was close to panic | F136: Anxiety | G136: FALSE | H136: FALSE | I136: Did not apply to me at all = 0 | Applied to me to some degree, or some of the time = 1 | Applied to me to a considerable degree, or a good part of time = 2 | Applied to me very much, or most of the time = 3 | K136: https://www2.psy.unsw.edu.au/dass/
A137: DASS-21 | B137: Depression Anxiety Stress Scales, 21 item version (DASS-21) | C137: 4. Psychological distress screening | D137: 16 | E137: I was unable to become enthusiastic about anything | F137: Depression | G137: FALSE | H137: FALSE | I137: Did not apply to me at all = 0 | Applied to me to some degree, or some of the time = 1 | Applied to me to a considerable degree, or a good part of time = 2 | Applied to me very much, or most of the time = 3 | K137: https://www2.psy.unsw.edu.au/dass/
A138: DASS-21 | B138: Depression Anxiety Stress Scales, 21 item version (DASS-21) | C138: 4. Psychological distress screening | D138: 17 | E138: I felt I wasn't worth much as a person | F138: Depression | G138: FALSE | H138: FALSE | I138: Did not apply to me at all = 0 | Applied to me to some degree, or some of the time = 1 | Applied to me to a considerable degree, or a good part of time = 2 | Applied to me very much, or most of the time = 3 | J138: Followed up directly when endorsed at 2 or 3 (practice protocol). | K138: https://www2.psy.unsw.edu.au/dass/
A139: DASS-21 | B139: Depression Anxiety Stress Scales, 21 item version (DASS-21) | C139: 4. Psychological distress screening | D139: 18 | E139: I felt that I was rather touchy | F139: Stress | G139: FALSE | H139: FALSE | I139: Did not apply to me at all = 0 | Applied to me to some degree, or some of the time = 1 | Applied to me to a considerable degree, or a good part of time = 2 | Applied to me very much, or most of the time = 3 | K139: https://www2.psy.unsw.edu.au/dass/
A140: DASS-21 | B140: Depression Anxiety Stress Scales, 21 item version (DASS-21) | C140: 4. Psychological distress screening | D140: 19 | E140: I was aware of the action of my heart in the absence of physical exertion (eg, sense of heart rate increase, heart missing a beat) | F140: Anxiety | G140: FALSE | H140: FALSE | I140: Did not apply to me at all = 0 | Applied to me to some degree, or some of the time = 1 | Applied to me to a considerable degree, or a good part of time = 2 | Applied to me very much, or most of the time = 3 | K140: https://www2.psy.unsw.edu.au/dass/
A141: DASS-21 | B141: Depression Anxiety Stress Scales, 21 item version (DASS-21) | C141: 4. Psychological distress screening | D141: 20 | E141: I felt scared without any good reason | F141: Anxiety | G141: FALSE | H141: FALSE | I141: Did not apply to me at all = 0 | Applied to me to some degree, or some of the time = 1 | Applied to me to a considerable degree, or a good part of time = 2 | Applied to me very much, or most of the time = 3 | K141: https://www2.psy.unsw.edu.au/dass/
A142: DASS-21 | B142: Depression Anxiety Stress Scales, 21 item version (DASS-21) | C142: 4. Psychological distress screening | D142: 21 | E142: I felt that life was meaningless | F142: Depression | G142: FALSE | H142: FALSE | I142: Did not apply to me at all = 0 | Applied to me to some degree, or some of the time = 1 | Applied to me to a considerable degree, or a good part of time = 2 | Applied to me very much, or most of the time = 3 | J142: Followed up directly when endorsed at 2 or 3 (practice protocol). | K142: https://www2.psy.unsw.edu.au/dass/
A143: PTQ | B143: Perseverative Thinking Questionnaire | C143: 5. Repetitive negative thinking and self talk | D143: 1 | E143: The same thoughts keep going through my mind again and again. | F143: Core Characteristics of Repetitive Negative Thinking | G143: FALSE | H143: FALSE | I143: never = 0 | rarely = 1 | sometimes = 2 | often = 3 | almost always = 4 | K143: https://oxcadatresources.com/wp-content/uploads/2020/09/EhringetalRuminationQuestionnaire.2011.pdf
A144: PTQ | B144: Perseverative Thinking Questionnaire | C144: 5. Repetitive negative thinking and self talk | D144: 2 | E144: Thoughts intrude into my mind. | F144: Core Characteristics of Repetitive Negative Thinking | G144: FALSE | H144: FALSE | I144: never = 0 | rarely = 1 | sometimes = 2 | often = 3 | almost always = 4 | K144: https://oxcadatresources.com/wp-content/uploads/2020/09/EhringetalRuminationQuestionnaire.2011.pdf
A145: PTQ | B145: Perseverative Thinking Questionnaire | C145: 5. Repetitive negative thinking and self talk | D145: 3 | E145: I can't stop dwelling on them. | F145: Core Characteristics of Repetitive Negative Thinking | G145: FALSE | H145: FALSE | I145: never = 0 | rarely = 1 | sometimes = 2 | often = 3 | almost always = 4 | K145: https://oxcadatresources.com/wp-content/uploads/2020/09/EhringetalRuminationQuestionnaire.2011.pdf
A146: PTQ | B146: Perseverative Thinking Questionnaire | C146: 5. Repetitive negative thinking and self talk | D146: 4 | E146: I think about many problems without solving any of them. | F146: Unproductiveness | G146: FALSE | H146: FALSE | I146: never = 0 | rarely = 1 | sometimes = 2 | often = 3 | almost always = 4 | K146: https://oxcadatresources.com/wp-content/uploads/2020/09/EhringetalRuminationQuestionnaire.2011.pdf
A147: PTQ | B147: Perseverative Thinking Questionnaire | C147: 5. Repetitive negative thinking and self talk | D147: 5 | E147: I can't do anything else while thinking about my problems. | F147: Capturing Mental Capacity | G147: FALSE | H147: FALSE | I147: never = 0 | rarely = 1 | sometimes = 2 | often = 3 | almost always = 4 | K147: https://oxcadatresources.com/wp-content/uploads/2020/09/EhringetalRuminationQuestionnaire.2011.pdf
A148: PTQ | B148: Perseverative Thinking Questionnaire | C148: 5. Repetitive negative thinking and self talk | D148: 6 | E148: My thoughts repeat themselves. | F148: Core Characteristics of Repetitive Negative Thinking | G148: FALSE | H148: FALSE | I148: never = 0 | rarely = 1 | sometimes = 2 | often = 3 | almost always = 4 | K148: https://oxcadatresources.com/wp-content/uploads/2020/09/EhringetalRuminationQuestionnaire.2011.pdf
A149: PTQ | B149: Perseverative Thinking Questionnaire | C149: 5. Repetitive negative thinking and self talk | D149: 7 | E149: Thoughts come to my mind without me wanting them to. | F149: Core Characteristics of Repetitive Negative Thinking | G149: FALSE | H149: FALSE | I149: never = 0 | rarely = 1 | sometimes = 2 | often = 3 | almost always = 4 | K149: https://oxcadatresources.com/wp-content/uploads/2020/09/EhringetalRuminationQuestionnaire.2011.pdf
A150: PTQ | B150: Perseverative Thinking Questionnaire | C150: 5. Repetitive negative thinking and self talk | D150: 8 | E150: I get stuck on certain issues and can't move on. | F150: Core Characteristics of Repetitive Negative Thinking | G150: FALSE | H150: FALSE | I150: never = 0 | rarely = 1 | sometimes = 2 | often = 3 | almost always = 4 | K150: https://oxcadatresources.com/wp-content/uploads/2020/09/EhringetalRuminationQuestionnaire.2011.pdf
A151: PTQ | B151: Perseverative Thinking Questionnaire | C151: 5. Repetitive negative thinking and self talk | D151: 9 | E151: I keep asking myself questions without finding an answer. | F151: Unproductiveness | G151: FALSE | H151: FALSE | I151: never = 0 | rarely = 1 | sometimes = 2 | often = 3 | almost always = 4 | K151: https://oxcadatresources.com/wp-content/uploads/2020/09/EhringetalRuminationQuestionnaire.2011.pdf
A152: PTQ | B152: Perseverative Thinking Questionnaire | C152: 5. Repetitive negative thinking and self talk | D152: 10 | E152: My thoughts prevent me from focusing on other things. | F152: Capturing Mental Capacity | G152: FALSE | H152: FALSE | I152: never = 0 | rarely = 1 | sometimes = 2 | often = 3 | almost always = 4 | K152: https://oxcadatresources.com/wp-content/uploads/2020/09/EhringetalRuminationQuestionnaire.2011.pdf
A153: PTQ | B153: Perseverative Thinking Questionnaire | C153: 5. Repetitive negative thinking and self talk | D153: 11 | E153: I keep thinking about the same issue all the time. | F153: Core Characteristics of Repetitive Negative Thinking | G153: FALSE | H153: FALSE | I153: never = 0 | rarely = 1 | sometimes = 2 | often = 3 | almost always = 4 | K153: https://oxcadatresources.com/wp-content/uploads/2020/09/EhringetalRuminationQuestionnaire.2011.pdf
A154: PTQ | B154: Perseverative Thinking Questionnaire | C154: 5. Repetitive negative thinking and self talk | D154: 12 | E154: Thoughts just pop into my mind. | F154: Core Characteristics of Repetitive Negative Thinking | G154: FALSE | H154: FALSE | I154: never = 0 | rarely = 1 | sometimes = 2 | often = 3 | almost always = 4 | K154: https://oxcadatresources.com/wp-content/uploads/2020/09/EhringetalRuminationQuestionnaire.2011.pdf
... A168: RRS | B168: Ruminative Responses Scale | C168: 5. Repetitive negative thinking and self talk | D168: 11 | E168: Go away by yourself and think about why you feel this way | F168: Reflection | G168: FALSE | H168: FALSE | I168: almost never = 1 | sometimes = 2 | often = 3 | almost always = 4 | K168: https://novopsych.com/assessments/formulation/ruminative-responses-scale-rrs/
A169: RRS | B169: Ruminative Responses Scale | C169: 5. Repetitive negative thinking and self talk | D169: 12 | E169: Write down what you are thinking about and analyze it | F169: Reflection | G169: FALSE | H169: FALSE | I169: almost never = 1 | sometimes = 2 | often = 3 | almost always = 4 | J169: Text as given in the original Nolen-Hoeksema item sheet (websites.umich.edu/~gonzo/RuminationScale.pdf). The Treynor et al. (2003) subscale-mapping paper quotes this item slightly differently, without "about" ("Write down what you are thinking and analyze it") — flagging the minor wording discrepancy between the two fetched sources. | K169: https://novopsych.com/assessments/formulation/ruminative-responses-scale-rrs/
A170: RRS | B170: Ruminative Responses Scale | C170: 5. Repetitive negative thinking and self talk | D170: 13 | E170: Think about a recent situation, wishing it had gone better | F170: Brooding | G170: FALSE | H170: FALSE | I170: almost never = 1 | sometimes = 2 | often = 3 | almost always = 4 | K170: https://novopsych.com/assessments/formulation/ruminative-responses-scale-rrs/
A171: RRS | B171: Ruminative Responses Scale | C171: 5. Repetitive negative thinking and self talk | D171: 14 | E171: Think "I won't be able to concentrate if I keep feeling this way" | F171: Depression-related items (not scored as a subscale) | G171: FALSE | H171: FALSE | I171: almost never = 1 | sometimes = 2 | often = 3 | almost always = 4 | K171: https://novopsych.com/assessments/formulation/ruminative-responses-scale-rrs/
A172: RRS | B172: Ruminative Responses Scale | C172: 5. Repetitive negative thinking and self talk | D172: 15 | E172: Think "Why do I have problems other people don't have?" | F172: Brooding | G172: FALSE | H172: FALSE | I172: almost never = 1 | sometimes = 2 | often = 3 | almost always = 4 | K172: https://novopsych.com/assessments/formulation/ruminative-responses-scale-rrs/
A173: RRS | B173: Ruminative Responses Scale | C173: 5. Repetitive negative thinking and self talk | D173: 16 | E173: Think "Why can't I handle things better?" | F173: Brooding | G173: FALSE | H173: FALSE | I173: almost never = 1 | sometimes = 2 | often = 3 | almost always = 4 | K173: https://novopsych.com/assessments/formulation/ruminative-responses-scale-rrs/
A174: RRS | B174: Ruminative Responses Scale | C174: 5. Repetitive negative thinking and self talk | D174: 17 | E174: Think about how sad you feel | F174: Depression-related items (not scored as a subscale) | G174: FALSE | H174: FALSE | I174: almost never = 1 | sometimes = 2 | often = 3 | almost always = 4 | K174: https://novopsych.com/assessments/formulation/ruminative-responses-scale-rrs/
A175: RRS | B175: Ruminative Responses Scale | C175: 5. Repetitive negative thinking and self talk | D175: 18 | E175: Think about all your shortcomings, failings, faults, mistakes | F175: Depression-related items (not scored as a subscale) | G175: FALSE | H175: FALSE | I175: almost never = 1 | sometimes = 2 | often = 3 | almost always = 4 | K175: https://novopsych.com/assessments/formulation/ruminative-responses-scale-rrs/
A176: RRS | B176: Ruminative Responses Scale | C176: 5. Repetitive negative thinking and self talk | D176: 19 | E176: Think about how you don't feel up to doing anything | F176: Depression-related items (not scored as a subscale) | G176: FALSE | H176: FALSE | I176: almost never = 1 | sometimes = 2 | often = 3 | almost always = 4 | K176: https://novopsych.com/assessments/formulation/ruminative-responses-scale-rrs/
A177: RRS | B177: Ruminative Responses Scale | C177: 5. Repetitive negative thinking and self talk | D177: 20 | E177: Analyze your personality to try to understand why you are depressed | F177: Reflection | G177: FALSE | H177: FALSE | I177: almost never = 1 | sometimes = 2 | often = 3 | almost always = 4 | K177: https://novopsych.com/assessments/formulation/ruminative-responses-scale-rrs/
A178: RRS | B178: Ruminative Responses Scale | C178: 5. Repetitive negative thinking and self talk | D178: 21 | E178: Go someplace alone to think about your feelings | F178: Reflection | G178: FALSE | H178: FALSE | I178: almost never = 1 | sometimes = 2 | often = 3 | almost always = 4 | K178: https://novopsych.com/assessments/formulation/ruminative-responses-scale-rrs/
A179: RRS | B179: Ruminative Responses Scale | C179: 5. Repetitive negative thinking and self talk | D179: 22 | E179: Think about how angry you are with yourself | F179: Depression-related items (not scored as a subscale) | G179: FALSE | H179: FALSE | I179: almost never = 1 | sometimes = 2 | often = 3 | almost always = 4 | K179: https://novopsych.com/assessments/formulation/ruminative-responses-scale-rrs/
A180: FSCRS | B180: Forms of Self-Criticising/Attacking and Self-Reassuring Scale | C180: 5. Repetitive negative thinking and self talk | D180: 1 | E180: I am easily disappointed with myself. | F180: Inadequate Self | G180: FALSE | H180: FALSE | I180: Not at all like me = 0 | A little bit like me = 1 | Moderately like me = 2 | Quite a bit like me = 3 | Extremely like me = 4 | K180: https://d3n8a8pro7vhmx.cloudfront.net/portlandpsychotherapy/pages/21/attachments/original/1438799410/Forms_of_self-criticising_and_self_reassuring_scale.pdf
A181: FSCRS | B181: Forms of Self-Criticising/Attacking and Self-Reassuring Scale | C181: 5. Repetitive negative thinking and self talk | D181: 2 | E181: There is a part of me that puts me down. | F181: Inadequate Self | G181: FALSE | H181: FALSE | I181: Not at all like me = 0 | A little bit like me = 1 | Moderately like me = 2 | Quite a bit like me = 3 | Extremely like me = 4 | K181: https://d3n8a8pro7vhmx.cloudfront.net/portlandpsychotherapy/pages/21/attachments/original/1438799410/Forms_of_self-criticising_and_self_reassuring_scale.pdf
... A187: FSCRS | B187: Forms of Self-Criticising/Attacking and Self-Reassuring Scale | C187: 5. Repetitive negative thinking and self talk | D187: 8 | E187: I still like being me. | F187: Reassured Self | G187: FALSE | H187: FALSE | I187: Not at all like me = 0 | A little bit like me = 1 | Moderately like me = 2 | Quite a bit like me = 3 | Extremely like me = 4 | K187: https://d3n8a8pro7vhmx.cloudfront.net/portlandpsychotherapy/pages/21/attachments/original/1438799410/Forms_of_self-criticising_and_self_reassuring_scale.pdf
A188: FSCRS | B188: Forms of Self-Criticising/Attacking and Self-Reassuring Scale | C188: 5. Repetitive negative thinking and self talk | D188: 9 | E188: I have become so angry with myself that I want to hurt or injure myself. | F188: Hated Self | G188: FALSE | H188: FALSE | I188: Not at all like me = 0 | A little bit like me = 1 | Moderately like me = 2 | Quite a bit like me = 3 | Extremely like me = 4 | J188: Sits close to self-harm content. Needs careful, consent-based framing in coaching: introduce only with appropriate rapport and a clear safety-checking plan for what happens if this item is endorsed, and treat any endorsement as a prompt for sensitive follow-up and referral consideration rather than something to work with in coaching alone. | K188: https://d3n8a8pro7vhmx.cloudfront.net/portlandpsychotherapy/pages/21/attachments/original/1438799410/Forms_of_self-criticising_and_self_reassuring_scale.pdf
A189: FSCRS | B189: Forms of Self-Criticising/Attacking and Self-Reassuring Scale | C189: 5. Repetitive negative thinking and self talk | D189: 10 | E189: I have a sense of disgust with myself. | F189: Hated Self | G189: FALSE | H189: FALSE | I189: Not at all like me = 0 | A little bit like me = 1 | Moderately like me = 2 | Quite a bit like me = 3 | Extremely like me = 4 | K189: https://d3n8a8pro7vhmx.cloudfront.net/portlandpsychotherapy/pages/21/attachments/original/1438799410/Forms_of_self-criticising_and_self_reassuring_scale.pdf
A190: FSCRS | B190: Forms of Self-Criticising/Attacking and Self-Reassuring Scale | C190: 5. Repetitive negative thinking and self talk | D190: 11 | E190: I can still feel lovable and acceptable. | F190: Reassured Self | G190: FALSE | H190: FALSE | I190: Not at all like me = 0 | A little bit like me = 1 | Moderately like me = 2 | Quite a bit like me = 3 | Extremely like me = 4 | K190: https://d3n8a8pro7vhmx.cloudfront.net/portlandpsychotherapy/pages/21/attachments/original/1438799410/Forms_of_self-criticising_and_self_reassuring_scale.pdf
A191: FSCRS | B191: Forms of Self-Criticising/Attacking and Self-Reassuring Scale | C191: 5. Repetitive negative thinking and self talk | D191: 12 | E191: I stop caring about myself. | F191: Hated Self | G191: FALSE | H191: FALSE | I191: Not at all like me = 0 | A little bit like me = 1 | Moderately like me = 2 | Quite a bit like me = 3 | Extremely like me = 4 | K191: https://d3n8a8pro7vhmx.cloudfront.net/portlandpsychotherapy/pages/21/attachments/original/1438799410/Forms_of_self-criticising_and_self_reassuring_scale.pdf
A192: FSCRS | B192: Forms of Self-Criticising/Attacking and Self-Reassuring Scale | C192: 5. Repetitive negative thinking and self talk | D192: 13 | E192: I find it easy to like myself. | F192: Reassured Self | G192: FALSE | H192: FALSE | I192: Not at all like me = 0 | A little bit like me = 1 | Moderately like me = 2 | Quite a bit like me = 3 | Extremely like me = 4 | K192: https://d3n8a8pro7vhmx.cloudfront.net/portlandpsychotherapy/pages/21/attachments/original/1438799410/Forms_of_self-criticising_and_self_reassuring_scale.pdf
A193: FSCRS | B193: Forms of Self-Criticising/Attacking and Self-Reassuring Scale | C193: 5. Repetitive negative thinking and self talk | D193: 14 | E193: I remember and dwell on my failings. | F193: Inadequate Self | G193: FALSE | H193: FALSE | I193: Not at all like me = 0 | A little bit like me = 1 | Moderately like me = 2 | Quite a bit like me = 3 | Extremely like me = 4 | K193: https://d3n8a8pro7vhmx.cloudfront.net/portlandpsychotherapy/pages/21/attachments/original/1438799410/Forms_of_self-criticising_and_self_reassuring_scale.pdf
A194: FSCRS | B194: Forms of Self-Criticising/Attacking and Self-Reassuring Scale | C194: 5. Repetitive negative thinking and self talk | D194: 15 | E194: I call myself names. | F194: Hated Self | G194: FALSE | H194: FALSE | I194: Not at all like me = 0 | A little bit like me = 1 | Moderately like me = 2 | Quite a bit like me = 3 | Extremely like me = 4 | K194: https://d3n8a8pro7vhmx.cloudfront.net/portlandpsychotherapy/pages/21/attachments/original/1438799410/Forms_of_self-criticising_and_self_reassuring_scale.pdf
A195: FSCRS | B195: Forms of Self-Criticising/Attacking and Self-Reassuring Scale | C195: 5. Repetitive negative thinking and self talk | D195: 16 | E195: I am gentle and supportive with myself. | F195: Reassured Self | G195: FALSE | H195: FALSE | I195: Not at all like me = 0 | A little bit like me = 1 | Moderately like me = 2 | Quite a bit like me = 3 | Extremely like me = 4 | K195: https://d3n8a8pro7vhmx.cloudfront.net/portlandpsychotherapy/pages/21/attachments/original/1438799410/Forms_of_self-criticising_and_self_reassuring_scale.pdf
A196: FSCRS | B196: Forms of Self-Criticising/Attacking and Self-Reassuring Scale | C196: 5. Repetitive negative thinking and self talk | D196: 17 | E196: I can't accept failures and setbacks without feeling inadequate. | F196: Inadequate Self | G196: FALSE | H196: FALSE | I196: Not at all like me = 0 | A little bit like me = 1 | Moderately like me = 2 | Quite a bit like me = 3 | Extremely like me = 4 | K196: https://d3n8a8pro7vhmx.cloudfront.net/portlandpsychotherapy/pages/21/attachments/original/1438799410/Forms_of_self-criticising_and_self_reassuring_scale.pdf
...

Sheet Structure and Subscales
A1: Code | B1: Instrument Name | C1: Domain | D1: Subscale / Theme / Strength | E1: Item Numbers | F1: Number of Items | G1: Score Range | H1: Description
A2: ESQ-R | B2: Executive Skills Questionnaire - Revised (ESQ-R) | C2: 1. Executive functioning and ADHD | D2: Plan Management | E2: 6-7, 12-14, 16-18, 22-24 | F2: 11 | G2: 0-33 | H2: Ability to create and manage plans for accomplishing tasks.
A3: ESQ-R | B3: Executive Skills Questionnaire - Revised (ESQ-R) | C3: 1. Executive functioning and ADHD | D3: Time Management | E3: 10-11, 15, 20 | F3: 4 | G3: 0-12 | H3: Ability to organize various aspects of time, including estimating and allocating time and working within time constraints.
A4: ESQ-R | B4: Executive Skills Questionnaire - Revised (ESQ-R) | C4: 1. Executive functioning and ADHD | D4: Organization | E4: 3, 8-9 | F4: 3 | G4: 0-9 | H4: Ability to create and maintain systems and keep track of information or materials.
A5: ESQ-R | B5: Executive Skills Questionnaire - Revised (ESQ-R) | C5: 1. Executive functioning and ADHD | D5: Emotional Regulation | E5: 4-5, 21 | F5: 3 | G5: 0-9 | H5: Ability to manage emotions to achieve goals, complete tasks, or control and direct behavior.
A6: ESQ-R | B6: Executive Skills Questionnaire - Revised (ESQ-R) | C6: 1. Executive functioning and ADHD | D6: Behavioral Regulation | E6: 1-2, 19, 25 | F6: 4 | G6: 0-12 | H6: Ability to manage behavior (avoid undesirable behaviors, increase desirable behaviors), think before acting or responding, and consider the consequences of actions.
A7: CFI | B7: Cognitive Flexibility Inventory (CFI) | C7: 1. Executive functioning and ADHD | D7: Alternatives | E7: 1, 3, 5-6, 8, 10, 12-14, 16, 18-20 | F7: 13 | G7: 13-91 | H7: Measures the ability to perceive multiple alternative explanations for life occurrences and human behaviour and the ability to generate multiple alternative solutions to difficult situations.
A8: CFI | B8: Cognitive Flexibility Inventory (CFI) | C8: 1. Executive functioning and ADHD | D8: Control | E8: 2, 4, 7, 9, 11, 15, 17 | F8: 7 | G8: 7-49 | H8: Measures the tendency to perceive difficult situations as controllable.
A9: ASRS | B9: Adult ADHD Self-Report Scale (ASRS v1.1) | C9: 1. Executive functioning and ADHD | D9: Part A (Criterion / Screener) | E9: 1-6 | F9: 6 | G9: 0-24 | H9: The six items most predictive of ADHD diagnosis (Kessler et al., 2007). Summed on the 0-4 Likert metric. Constitutes the six-item ASRS Screener when used alone.
A10: ASRS | B10: Adult ADHD Self-Report Scale (ASRS v1.1) | C10: 1. Executive functioning and ADHD | D10: Part B (Additional Symptoms) | E10: 7-18 | F10: 12 | G10: 0-48 | H10: Twelve additional DSM-based items providing a broader index of symptom severity and further probes into the client's symptoms.
A11: ASRS | B11: Adult ADHD Self-Report Scale (ASRS v1.1) | C11: 1. Executive functioning and ADHD | D11: Inattentiveness | E11: 1-4, 7-11 | F11: 9 | G11: 0-9 (dichotomous symptom count) | H11: Stanton et al. (2018) factor. Difficulty focussing on details, being organised, remembering appointments, making careless mistakes, and concentrating. Scored using the original dichotomous method (0 or 1 per item) and reported as number and percentage of items endorsed.
A12: ASRS | B12: Adult ADHD Self-Report Scale (ASRS v1.1) | C12: 1. Executive functioning and ADHD | D12: Hyperactivity/Impulsivity - Motor | E12: 5-6, 12-14 | F12: 5 | G12: 0-5 (dichotomous symptom count) | H12: Stanton et al. (2018) factor. Difficulty sitting still, staying seated, and ability to relax.
A13: ASRS | B13: Adult ADHD Self-Report Scale (ASRS v1.1) | C13: 1. Executive functioning and ADHD | D13: Hyperactivity/Impulsivity - Verbal | E13: 15-18 | F13: 4 | G13: 0-4 (dichotomous symptom count) | H13: Stanton et al. (2018) factor. Difficulty controlling how much they talk, interrupting others, and waiting their turn.
... A52: PCI | B52: Perfectionism Cognitions Inventory | C52: 5. Repetitive negative thinking and self talk | D52: Perfectionism Cognitions (total scale) | E52: 1-25 | F52: 25 | G52: 0-100 | H52: Single total score; higher means more frequent perfectionistic thoughts. Row added for the hub.

Sheet References
A1: Code | B1: Instrument Name | C1: Domain | D1: Type | E1: Citation (APA 7)
A2: ESQ-R | B2: Executive Skills Questionnaire - Revised (ESQ-R) | C2: 1. Executive functioning and ADHD | D2: Developer | E2: Developed by Dr. Peg Dawson (Smart But Scattered Kids). Original citation: Strait, J. E., Dawson, P., Walther, C. A. P., Strait, G. G., Barton, A. K., & McClain, M. B. (2020). Refinement and psychometric evaluation of the Executive Skills Questionnaire-Revised. Contemporary School Psychology, 24, 378-388. https://doi.org/10.1007/s40688-018-00224-x
A3: ESQ-R | B3: Executive Skills Questionnaire - Revised (ESQ-R) | C3: 1. Executive functioning and ADHD | D3: Reference | E3: Strait, J. E., Dawson, P., Walther, C. A. P., Strait, G. G., Barton, A. K., & McClain, M. B. (2020). Refinement and psychometric evaluation of the Executive Skills Questionnaire-Revised. Contemporary School Psychology, 24, 378-388. https://doi.org/10.1007/s40688-018-00224-x
A4: ESQ-R | B4: Executive Skills Questionnaire - Revised (ESQ-R) | C4: 1. Executive functioning and ADHD | D4: Reference | E4: Aksayli, N. D., Sala, G., & Gobet, F. (2019). The cognitive and academic benefits of Cogmed: A meta-analysis. Educational Research Review, 27, 229-243. https://doi.org/10.1016/j.edurev.2019.04.003
A5: ESQ-R | B5: Executive Skills Questionnaire - Revised (ESQ-R) | C5: 1. Executive functioning and ADHD | D5: Reference | E5: Craig, F., Margari, F., Legrottaglie, A. R., Palumbi, R., de Giambattista, C., & Margari, L. (2016). A review of executive function deficits in autism spectrum disorder and attention-deficit/hyperactivity disorder. Neuropsychiatric Disease and Treatment, 12, 1191-1202. https://doi.org/10.2147/NDT.S104620
A6: ESQ-R | B6: Executive Skills Questionnaire - Revised (ESQ-R) | C6: 1. Executive functioning and ADHD | D6: Reference | E6: Dawson, P., & Guare, R. (2018). Executive skills in children and adolescents: A practical guide to assessment and intervention (3rd ed.). The Guilford Press.
A7: ESQ-R | B7: Executive Skills Questionnaire - Revised (ESQ-R) | C7: 1. Executive functioning and ADHD | D7: Reference | E7: Miyake, A., Friedman, N. P., Emerson, M. J., Witzki, A. H., Howerter, A., & Wager, T. D. (2000). The unity and diversity of executive functions and their contributions to complex 'frontal lobe' tasks: A latent variable analysis. Cognitive Psychology, 41, 49-100. https://doi.org/10.1006/cogp.1999.0734
A8: ESQ-R | B8: Executive Skills Questionnaire - Revised (ESQ-R) | C8: 1. Executive functioning and ADHD | D8: Reference | E8: Nasir, H., Tan, C. S., & Pheh, K. S. (2021). The Executive Skills Questionnaire-Revised: Adaptation and psychometric properties in the working context of Malaysia. International Journal of Environmental Research and Public Health, 18(17), 8978. https://doi.org/10.3390/ijerph18178978
A9: CFI | B9: Cognitive Flexibility Inventory (CFI) | C9: 1. Executive functioning and ADHD | D9: Developer | E9: Dennis, J. P., & Vander Wal, J. S. (2010). The cognitive flexibility inventory: Instrument development and estimates of reliability and validity. Cognitive Therapy and Research, 34(3), 241-253. https://doi.org/10.1007/s10608-009-9276-4
A10: CFI | B10: Cognitive Flexibility Inventory (CFI) | C10: 1. Executive functioning and ADHD | D10: Reference | E10: Johnco, C., Wuthrich, V. M., & Rapee, R. M. (2014). Reliability and validity of two self-report measures of cognitive flexibility. Psychological Assessment, 26(4), 1381-1387. https://doi.org/10.1037/a0038009
A11: ASRS | B11: Adult ADHD Self-Report Scale (ASRS v1.1) | C11: 1. Executive functioning and ADHD | D11: Developer | E11: Kessler, R. C., Adler, L., Ames, M., Demler, O., Faraone, S., Hiripi, E., Howes, M. J., Jin, R., Secnik, K., Spencer, T., Ustun, T. B., & Walters, E. E. (2005). The World Health Organization Adult ADHD Self-Report Scale (ASRS): a short screening scale for use in the general population. Psychological Medicine, 35(2), 245-256. https://doi.org/10.1017/s0033291704002892
A12: ASRS | B12: Adult ADHD Self-Report Scale (ASRS v1.1) | C12: 1. Executive functioning and ADHD | D12: Reference | E12: Adler, L. A., Faraone, S. V., Sarocco, P., Atkins, N., & Khachatryan, A. (2019). Establishing US norms for the Adult ADHD Self-Report Scale (ASRS-v1.1) and characterising symptom burden among adults with self-reported ADHD. International Journal of Clinical Practice, 73(1), e13260. https://doi.org/10.1111/ijcp.13260
... A62: GADJ | B62: Goal Adjustment Scale | C62: 6. Motivation, self determination and goal pursuit | D62: Developer | E62: Wrosch, C., Scheier, M. F., Miller, G. E., Schulz, R., & Carver, C. S. (2003). Adaptive self-regulation of unattainable goals: Goal disengagement, goal reengagement, and subjective well-being. Personality and Social Psychology Bulletin, 29(12), 1494-1508.

Sheet ESQ-R
A1: Executive Skills Questionnaire - Revised (ESQ-R)
A3: Instrument | B3: Executive Skills Questionnaire - Revised (ESQ-R)
A4: Code | B4: ESQ-R
A5: Domain | B5: 1. Executive functioning and ADHD
A6: Availability | B6: Free / open access
A7: Construct | B7: Executive functioning skills, including plan and time management, organization, and emotional and behavioral regulation
A8: Respondent | B8: Self-report
A9: Age range | B9: 14+
A10: Items in instrument | B10: 25
A11: Items reproduced here | B11: 25
A12: Administration time | B12: 5 minutes
A13: Cost and access | B13: Included on NovoPsych with the permission of Dr Peg Dawson; blank form hosted free. Scoring and percentiles need a NovoPsych account.
A14: Coaching application | B14: The core executive skills profile for coaching; the five subscales map directly onto coaching targets. Measures higher order skills rather than core executive functions.
... A27: Source URL | B27: https://novopsych.com/assessments/formulation/executive-skills-questionnaire-revised-esq-r/
A29: Item Number | B29: Item Text (verbatim) | C29: Subscale / Domain | D29: Reverse | E29: Filler | F29: Item Notes
A30: 1 | B30: I act on impulse. | C30: Behavioral Regulation | D30: FALSE | E30: FALSE
A31: 2 | B31: I say things without thinking. | C31: Behavioral Regulation | D31: FALSE | E31: FALSE
A32: 3 | B32: I lose things. | C32: Organization | D32: FALSE | E32: FALSE
A33: 4 | B33: I have a short fuse. | C33: Emotional Regulation | D33: FALSE | E33: FALSE
A34: 5 | B34: I get upset when things don't go as planned. | C34: Emotional Regulation | D34: FALSE | E34: FALSE
A35: 6 | B35: I run out of steam before finishing a task. | C35: Plan Management | D35: FALSE | E35: FALSE
A36: 7 | B36: It's hard for me to set priorities when I have a lot of things to do. | C36: Plan Management | D36: FALSE | E36: FALSE
A37: 8 | B37: My desk or workspace is a mess. | C37: Organization | D37: FALSE | E37: FALSE
A38: 9 | B38: I have trouble keeping my house or room clean. | C38: Organization | D38: FALSE | E38: FALSE
A39: 10 | B39: I have trouble estimating how long it will take to complete a task. | C39: Time Management | D39: FALSE | E39: FALSE
A40: 11 | B40: I'm slow at getting ready for school, work, or appointments. | C40: Time Management | D40: FALSE | E40: FALSE
A41: 12 | B41: If the first solution to a problem doesn't work, I have trouble thinking of a different one. | C41: Plan Management | D41: FALSE | E41: FALSE
... A54: 25 | B54: I live for the moment. | C54: Behavioral Regulation | D54: FALSE | E54: FALSE

Sheet CFI
A1: Cognitive Flexibility Inventory (CFI)
A3: Instrument | B3: Cognitive Flexibility Inventory (CFI)
A4: Code | B4: CFI
A5: Domain | B5: 1. Executive functioning and ADHD
A6: Availability | B6: Free / open access
A7: Construct | B7: Cognitive flexibility - the ability to perceive multiple alternative explanations for life occurrences and human behaviour, generate multiple alternative solutions to difficult situations, and perceive difficult situations as controllable
A8: Respondent | B8: Self-report
A9: Age range | B9: 18+
A10: Items in instrument | B10: 20
A11: Items reproduced here | B11: 20
A12: Administration time | B12: 3 minutes
A13: Cost and access | B13: Published in Dennis and Vander Wal (2010); blank form hosted free on NovoPsych.
A14: Coaching application | B14: Measures cognitive flexibility, useful for tracking response to reframing and problem solving work. Scored in the opposite direction to the ESQ-R.
... A27: Source URL | B27: https://novopsych.com/assessments/formulation/cognitive-flexibility-inventory-cfi/
A29: Item Number | B29: Item Text (verbatim) | C29: Subscale / Domain | D29: Reverse | E29: Filler | F29: Item Notes
A30: 1 | B30: I am good at "sizing up" situations. | C30: Alternatives | D30: FALSE | E30: FALSE
A31: 2 | B31: I have a hard time making decisions when faced with difficult situations. | C31: Control | D31: TRUE | E31: FALSE
A32: 3 | B32: I consider multiple options before making a decision. | C32: Alternatives | D32: FALSE | E32: FALSE
A33: 4 | B33: When I encounter difficult situations, I feel like I am losing control. | C33: Control | D33: TRUE | E33: FALSE
A34: 5 | B34: I like to look at difficult situations from many different angles. | C34: Alternatives | D34: FALSE | E34: FALSE
A35: 6 | B35: I seek additional information not immediately available before attributing causes to behaviour. | C35: Alternatives | D35: FALSE | E35: FALSE
A36: 7 | B36: When encountering difficult situations, I become so stressed that I can not think of a way to resolve the situation. | C36: Control | D36: TRUE | E36: FALSE
A37: 8 | B37: I try to think about things from another person's point of view. | C37: Alternatives | D37: FALSE | E37: FALSE
A38: 9 | B38: I find it troublesome that there are so many different ways to deal with difficult situations. | C38: Control | D38: TRUE | E38: FALSE
A39: 10 | B39: I am good at putting myself in others' shoes. | C39: Alternatives | D39: FALSE | E39: FALSE
A40: 11 | B40: When I encounter difficult situations, I just don't know what to do. | C40: Control | D40: TRUE | E40: FALSE
A41: 12 | B41: It is important to look at difficult situations from many angles. | C41: Alternatives | D41: FALSE | E41: FALSE
... A49: 20 | B49: I consider multiple options before responding to difficult situations. | C49: Alternatives | D49: FALSE | E49: FALSE

Sheet ASRS
A1: Adult ADHD Self-Report Scale (ASRS v1.1)
A3: Instrument | B3: Adult ADHD Self-Report Scale (ASRS v1.1)
A4: Code | B4: ASRS
A5: Domain | B5: 1. Executive functioning and ADHD
A6: Availability | B6: Free / open access
A7: Construct | B7: Attention Deficit Hyperactivity Disorder (ADHD) symptoms in adults, spanning inattentiveness and hyperactivity/impulsivity (including motor and verbal components)
A8: Respondent | B8: self-report
A9: Age range | B9: 18+
A10: Items in instrument | B10: 18
A11: Items reproduced here | B11: 18
A12: Administration time | B12: 3 minutes
A13: Cost and access | B13: Public domain WHO instrument. Blank form hosted free on NovoPsych; scoring and reports need a NovoPsych account.
A14: Coaching application | B14: Screening and severity measure for current adult ADHD symptoms; pairs with the WURS-25 for childhood history. Not a diagnostic instrument on its own.
... A27: Source URL | B27: https://novopsych.com/assessments/diagnosis/adult-adhd-self-report-scale-asrs/
A29: Item Number | B29: Item Text (verbatim) | C29: Subscale / Domain | D29: Reverse | E29: Filler | F29: Item Notes
A30: 1 | B30: How often do you have trouble wrapping up the final details of a project, once the challenging parts have been done? | C30: Part A | Inattentiveness | D30: FALSE | E30: FALSE
A31: 2 | B31: How often do you have difficulty getting things in order when you have to do a task that requires organisation? | C31: Part A | Inattentiveness | D31: FALSE | E31: FALSE
A32: 3 | B32: How often do you have problems remembering appointments or obligations? | C32: Part A | Inattentiveness | D32: FALSE | E32: FALSE
A33: 4 | B33: When you have a task that requires a lot of thought, how often do you avoid or delay getting started? | C33: Part A | Inattentiveness | D33: FALSE | E33: FALSE
A34: 5 | B34: How often do you fidget or squirm with your hands or feet when you have to sit down for a long time? | C34: Part A | Hyperactivity/Impulsivity - Motor | D34: FALSE | E34: FALSE
A35: 6 | B35: How often do you feel overly active and compelled to do things, like you were driven by a motor? | C35: Part A | Hyperactivity/Impulsivity - Motor | D35: FALSE | E35: FALSE
A36: 7 | B36: How often do you make careless mistakes when you have to work on a boring or difficult project? | C36: Part B | Inattentiveness | D36: FALSE | E36: FALSE
A37: 8 | B37: How often do you have difficulty keeping your attention when you are doing boring or repetitive work? | C37: Part B | Inattentiveness | D37: FALSE | E37: FALSE
A38: 9 | B38: How often do you have difficulty concentrating on what people say to you, even when they are speaking to you directly? | C38: Part B | Inattentiveness | D38: FALSE | E38: FALSE
A39: 10 | B39: How often do you misplace or have difficulty finding things at home or at work? | C39: Part B | Inattentiveness | D39: FALSE | E39: FALSE
A40: 11 | B40: How often are you distracted by activity or noise around you? | C40: Part B | Inattentiveness | D40: FALSE | E40: FALSE
A41: 12 | B41: How often do you leave your seat in meetings or other situations in which you are expected to remain seated? | C41: Part B | Hyperactivity/Impulsivity - Motor | D41: FALSE | E41: FALSE
... A47: 18 | B47: How often do you interrupt others when they are busy? | C47: Part B | Hyperactivity/Impulsivity - Verbal | D47: FALSE | E47: FALSE

Sheet SKS
A1: Strengths Knowledge Scale
A3: Instrument | B3: Strengths Knowledge Scale
A4: Code | B4: SKS
A5: Domain | B5: 2. Strengths knowledge, use and support at work
A6: Availability | B6: Free / open access
A7: Construct | B7: Perceived self-knowledge of one's own personal strengths, i.e. the extent to which a person is aware of what they do best.
A8: Respondent | B8: Self-report
A9: Age range | B9: Adults and university students; used in adolescent samples (secondary school age) in later validations, but the original 2007 development sample was working adults
A10: Items in instrument | B10: 8
A11: Items reproduced here | B11: 8
A12: Administration time | B12: 2-3 minutes
A13: Cost and access | B13: No licence fee or permission is required to use the SKS in coaching practice. The scale was published in full within the original journal article (Govindji & Linley, 2007, International Coaching Psychology Review, a BPS Special Group in Coaching Psychology publication) and has since been reproduced verbatim in several open-access peer-reviewed validation papers (e.g. the Frontiers in Psychology 2023 Spanish validation used as the source for this record). A practitioner can administer it as a simple paper or online 7-point rating form; no test manual, scoring software or purchase is needed. The original 2007 article itself is not reliably available as an open PDF (International Coaching Psychology Review back issues are not consistently hosted online), so items here were transcribed from an open-access reproduction rather than the original publication.
A14: Coaching application | B14: The SKS is useful early in strengths coaching to establish a baseline of how well a client can already name and recognise their own best qualities, which shapes whether initial sessions should focus on strength identification (e.g. via VIA or Realise2) before moving to strengths use. Low scores flag clients who may benefit from structured strength-spotting exercises, feedback from others, or a formal strengths assessment before goal-setting. Its main limit is that it only captures self-perceived awareness, not accuracy of that self-knowledge, so it should be paired with an objective strengths measure or 360-degree feedback rather than used alone to confirm what a client's real strengths are.
... A27: Source URL | B27: https://www.frontiersin.org/journals/psychology/articles/10.3389/fpsyg.2023.1086510/full
A29: Item Number | B29: Item Text (verbatim) | C29: Subscale / Domain | D29: Reverse | E29: Filler | F29: Item Notes
A30: 1 | B30: Other people see the strengths that I have | C30: Strengths Knowledge (total scale) | D30: FALSE | E30: FALSE | F30: Verbatim as reproduced in Frontiers in Psychology (2023), Table 5, citing Govindji & Linley (2007).
A31: 2 | B31: I have to think hard about what my strengths are | C31: Strengths Knowledge (total scale) | D31: FALSE | E31: FALSE | F31: Verbatim as reproduced in Frontiers in Psychology (2023), Table 5. One secondary aggregator source (db.arabpsychology.com) describes this item as reverse-scored, but the Frontiers (2023) reproduction directly consulted for this record states no reverse-scored items are present for either scale, so reverse scoring for this item could not be independently confirmed and is left unmarked pending sight of the original 2007 scoring key.
A32: 3 | B32: I know what I do best | C32: Strengths Knowledge (total scale) | D32: FALSE | E32: FALSE | F32: Verbatim as reproduced in Frontiers in Psychology (2023), Table 5.
A33: 4 | B33: I am aware of my strengths | C33: Strengths Knowledge (total scale) | D33: FALSE | E33: FALSE | F33: Verbatim as reproduced in Frontiers in Psychology (2023), Table 5.
A34: 5 | B34: I know the things I am good at doing | C34: Strengths Knowledge (total scale) | D34: FALSE | E34: FALSE | F34: Verbatim as reproduced in Frontiers in Psychology (2023), Table 5.
A35: 6 | B35: I know my strengths well | C35: Strengths Knowledge (total scale) | D35: FALSE | E35: FALSE | F35: Verbatim as reproduced in Frontiers in Psychology (2023), Table 5.
A36: 7 | B36: I know the things I do best | C36: Strengths Knowledge (total scale) | D36: FALSE | E36: FALSE | F36: Verbatim as reproduced in Frontiers in Psychology (2023), Table 5.
A37: 8 | B37: I know when I am at my best | C37: Strengths Knowledge (total scale) | D37: FALSE | E37: FALSE | F37: Verbatim as reproduced in Frontiers in Psychology (2023), Table 5.

Sheet SUS
A1: Strengths Use Scale
A3: Instrument | B3: Strengths Use Scale
A4: Code | B4: SUS
A5: Domain | B5: 2. Strengths knowledge, use and support at work
A6: Availability | B6: Free / open access
A7: Construct | B7: Perceived deployment of one's own personal strengths in daily life, i.e. the extent to which a person actively uses what they do best across situations.
A8: Respondent | B8: Self-report
A9: Age range | B9: Adults and university students; used in adolescent samples (secondary school age) in later validations, but the original 2007 development sample was working adults
A10: Items in instrument | B10: 14
A11: Items reproduced here | B11: 14
A12: Administration time | B12: 3-5 minutes
A13: Cost and access | B13: No licence fee or permission is required to use the SUS in coaching practice. The scale was published in full within the original journal article (Govindji & Linley, 2007, International Coaching Psychology Review, a BPS Special Group in Coaching Psychology publication) and has since been reproduced verbatim in several open-access peer-reviewed validation papers (e.g. the Frontiers in Psychology 2023 Spanish validation used as the source for this record). It can be administered as a simple paper or online 7-point rating form; no manual, scoring software or purchase is needed. The original 2007 article itself is not reliably available as an open PDF (International Coaching Psychology Review back issues are not consistently hosted online), so items here were transcribed from an open-access reproduction rather than the original publication.
A14: Coaching application | B14: The SUS is well suited to tracking a client's progress in strengths coaching over time, since it directly measures how often and how naturally strengths are being deployed at work, study and in life generally, which is the practical outcome most strengths coaching aims to move. It works well as a short pre/post measure around a block of coaching focused on applying identified strengths to goals. Its limit is that it assumes the client already knows what their strengths are (it should usually follow, not replace, a strengths-identification step such as VIA or the SKS) and it captures frequency and ease of use rather than the fit or appropriateness of how strengths are being applied.
... A27: Source URL | B27: https://www.frontiersin.org/journals/psychology/articles/10.3389/fpsyg.2023.1086510/full
A29: Item Number | B29: Item Text (verbatim) | C29: Subscale / Domain | D29: Reverse | E29: Filler | F29: Item Notes
A30: 1 | B30: I am regularly able to do what I do best. | C30: Strengths Use (total scale) | D30: FALSE | E30: FALSE | F30: Verbatim as reproduced in Frontiers in Psychology (2023), Table 2, citing Govindji & Linley (2007).
A31: 2 | B31: I always play to my strengths. | C31: Strengths Use (total scale) | D31: FALSE | E31: FALSE | F31: Verbatim as reproduced in Frontiers in Psychology (2023), Table 2.
A32: 3 | B32: I always try to use my strengths. | C32: Strengths Use (total scale) | D32: FALSE | E32: FALSE | F32: Verbatim as reproduced in Frontiers in Psychology (2023), Table 2.
A33: 4 | B33: I achieve what I want by using my strengths. | C33: Strengths Use (total scale) | D33: FALSE | E33: FALSE | F33: Verbatim as reproduced in Frontiers in Psychology (2023), Table 2.
A34: 5 | B34: I use my strengths every day. | C34: Strengths Use (total scale) | D34: FALSE | E34: FALSE | F34: Verbatim as reproduced in Frontiers in Psychology (2023), Table 2.
A35: 6 | B35: I use my strengths to get what I want out of life. | C35: Strengths Use (total scale) | D35: FALSE | E35: FALSE | F35: Verbatim as reproduced in Frontiers in Psychology (2023), Table 2.
A36: 7 | B36: My work gives me lots of opportunities to use my strengths. | C36: Strengths Use (total scale) | D36: FALSE | E36: FALSE | F36: Verbatim as reproduced in Frontiers in Psychology (2023), Table 2.
A37: 8 | B37: My life presents me with lots of different ways to use my strengths. | C37: Strengths Use (total scale) | D37: FALSE | E37: FALSE | F37: Verbatim as reproduced in Frontiers in Psychology (2023), Table 2.
A38: 9 | B38: Using my strengths comes naturally to me. | C38: Strengths Use (total scale) | D38: FALSE | E38: FALSE | F38: Verbatim as reproduced in Frontiers in Psychology (2023), Table 2.
A39: 10 | B39: I find it easy to use my strengths in the things I do. | C39: Strengths Use (total scale) | D39: FALSE | E39: FALSE | F39: Verbatim as reproduced in Frontiers in Psychology (2023), Table 2.
A40: 11 | B40: I am able to use my strengths in lots of different situations. | C40: Strengths Use (total scale) | D40: FALSE | E40: FALSE | F40: Verbatim as reproduced in Frontiers in Psychology (2023), Table 2.
A41: 12 | B41: Most of my time is spent doing the things that I am good at doing. | C41: Strengths Use (total scale) | D41: FALSE | E41: FALSE | F41: Verbatim as reproduced in Frontiers in Psychology (2023), Table 2.
... A43: 14 | B43: I am able to use my strengths in lots of different ways. | C43: Strengths Use (total scale) | D43: FALSE | E43: FALSE | F43: Verbatim as reproduced in Frontiers in Psychology (2023), Table 2.

Sheet SSES
A1: Strengths Self-Efficacy Scale
A3: Instrument | B3: Strengths Self-Efficacy Scale
A4: Code | B4: SSES
A5: Domain | B5: 2. Strengths knowledge, use and support at work
A6: Availability | B6: Free / open access
A7: Construct | B7: Perceived self-efficacy (confidence) in one's ability to identify, apply and use one's personal strengths across everyday situations, at work or study, and in pursuit of goals.
A8: Respondent | B8: Self-report
A9: Age range | B9: Adults; validated with U.S. college students and working adults, applicable to late-secondary and university-age coaching clients
A10: Items in instrument | B10: 11
A11: Items reproduced here | B11: 11
A12: Administration time | B12: 3-5 minutes
A13: Cost and access | B13: The SSES is free to use for practice and research; the full 11-item form (with its instructions, five-signature-strengths preamble, and 10-point response scale) is published as an open-access downloadable PDF by PositivePsychology.com, and the same item wording is corroborated by an independent academic reproduction. No licence fee or formal permission is required, though practitioners should cite Tsai, Chaichanasakul, Zhao, Flores and Lopez (2014) as the scale's developers. The original peer-reviewed validation article is behind a SAGE subscription paywall (Journal of Career Assessment).
A14: Coaching application | B14: The SSES is a good fit for strengths-based career and academic coaching because it measures confidence in actually applying strengths, which is the practical skill most coaching aims to build, and it can be re-administered after a coaching block to check whether a client's confidence in using their strengths has shifted. Because it asks respondents to first name their own five signature strengths, it works well paired with a prior strengths-identification step (VIA, Realise2, or the SKS/SUS above). Its limit is that it measures perceived confidence rather than actual competent strengths use, so a client can score highly while still using strengths in an unhelpful or overextended way, and low scores need follow-up to distinguish a genuine skills gap from low self-belief alone.
... A27: Source URL | B27: https://positivepsychology.com/wp-content/uploads/The-Strengths-Self-efficacy-Scale.pdf
A29: Item Number | B29: Item Text (verbatim) | C29: Subscale / Domain | D29: Reverse | E29: Filler | F29: Item Notes
A30: 1 | B30: Use your strengths at work? | C30: Strengths Self-Efficacy (total scale) | D30: FALSE | E30: FALSE | F30: Verbatim as reproduced in the PositivePsychology.com PDF and corroborated by an independent academia.edu reproduction, both stemmed from "How confident are you in your ability to ...."
A31: 2 | B31: Use your strengths without any struggles? | C31: Strengths Self-Efficacy (total scale) | D31: FALSE | E31: FALSE | F31: Verbatim as reproduced in the PositivePsychology.com PDF, corroborated by academia.edu reproduction.
A32: 3 | B32: Find ways to apply your strengths in the things you do everyday? | C32: Strengths Self-Efficacy (total scale) | D32: FALSE | E32: FALSE | F32: Verbatim as reproduced in the PositivePsychology.com PDF, corroborated by academia.edu reproduction.
A33: 4 | B33: Accomplish a lot using your strengths? | C33: Strengths Self-Efficacy (total scale) | D33: FALSE | E33: FALSE | F33: Verbatim as reproduced in the PositivePsychology.com PDF, corroborated by academia.edu reproduction.
A34: 5 | B34: Apply your strengths at work/school? | C34: Strengths Self-Efficacy (total scale) | D34: FALSE | E34: FALSE | F34: Verbatim as reproduced in the PositivePsychology.com PDF, corroborated by academia.edu reproduction.
A35: 6 | B35: Use your strengths in many situations? | C35: Strengths Self-Efficacy (total scale) | D35: FALSE | E35: FALSE | F35: Verbatim as reproduced in the PositivePsychology.com PDF, corroborated by academia.edu reproduction.
A36: 7 | B36: Use your strengths to succeed? | C36: Strengths Self-Efficacy (total scale) | D36: FALSE | E36: FALSE | F36: Verbatim as reproduced in the PositivePsychology.com PDF, corroborated by academia.edu reproduction.
A37: 8 | B37: Find ways to use your strengths at work/school everyday? | C37: Strengths Self-Efficacy (total scale) | D37: FALSE | E37: FALSE | F37: Verbatim as reproduced in the PositivePsychology.com PDF, corroborated by academia.edu reproduction.
A38: 9 | B38: Use your strengths at any time? | C38: Strengths Self-Efficacy (total scale) | D38: FALSE | E38: FALSE | F38: Verbatim as reproduced in the PositivePsychology.com PDF, corroborated by academia.edu reproduction.
A39: 10 | B39: Use your strengths to help you achieve your goals in life? | C39: Strengths Self-Efficacy (total scale) | D39: FALSE | E39: FALSE | F39: Verbatim as reproduced in the PositivePsychology.com PDF, corroborated by academia.edu reproduction.
A40: 11 | B40: Practice your strengths in areas where you excel? | C40: Strengths Self-Efficacy (total scale) | D40: FALSE | E40: FALSE | F40: Verbatim as reproduced in the PositivePsychology.com PDF, corroborated by academia.edu reproduction.

Sheet CSES
A1: Core Self-Evaluations Scale
A3: Instrument | B3: Core Self-Evaluations Scale
A4: Code | B4: CSES
A5: Domain | B5: 3. Adjacent occupational and wellbeing
A6: Availability | B6: Free / open access
A7: Construct | B7: Core self-evaluations: a broad, fundamental positive self-appraisal trait combining self-esteem, generalised self-efficacy, internal locus of control and low neuroticism (emotional stability).
A8: Respondent | B8: Self-report
A9: Age range | B9: Working adults (Samples 1-2 of the original validation); also validated with university undergraduates (Samples 3-4). Suitable for university-age and early-career coaching clients.
A10: Items in instrument | B10: 12
A11: Items reproduced here | B11: 12
A12: Administration time | B12: 2-3 minutes
A13: Cost and access | B13: The scale is explicitly stated by the developers to be non-proprietary and free to use without permission. The full 12-item scale, with response format and scoring key, is reproduced in an open PDF of the original SIOP conference/journal materials.
A14: Coaching application | B14: The CSES is useful as a brief baseline measure of a student or early-career client's general positive self-appraisal (self-esteem, self-efficacy, sense of control) at the start of a coaching relationship, and can flag when low scores on 'control' or 'competence' items point to executive-function or confidence work rather than a skills gap. It is not a strengths-identification tool and should not be presented to a client as diagnostic; its brevity and free licence make it practical for repeat use, but coaches should be alert that several reverse-scored items touch on depressed mood and hopelessness, which needs sensitive framing with any client where wellbeing is a live concern.
... A27: Source URL | B27: http://ionilies.com/SIOP03/Files/CSES.pdf
A29: Item Number | B29: Item Text (verbatim) | C29: Subscale / Domain | D29: Reverse | E29: Filler | F29: Item Notes
A30: 1 | B30: I am confident I get the success I deserve in life. | C30: Core Self-Evaluations (total scale, unidimensional) | D30: FALSE | E30: FALSE
A31: 2 | B31: Sometimes I feel depressed. | C31: Core Self-Evaluations (total scale, unidimensional) | D31: TRUE | E31: FALSE | F31: Touches on depressed mood; use sensitively with clients where wellbeing is a live concern.
A32: 3 | B32: When I try, I generally succeed. | C32: Core Self-Evaluations (total scale, unidimensional) | D32: FALSE | E32: FALSE
A33: 4 | B33: Sometimes when I fail I feel worthless. | C33: Core Self-Evaluations (total scale, unidimensional) | D33: TRUE | E33: FALSE
A34: 5 | B34: I complete tasks successfully. | C34: Core Self-Evaluations (total scale, unidimensional) | D34: FALSE | E34: FALSE
A35: 6 | B35: Sometimes, I do not feel in control of my work. | C35: Core Self-Evaluations (total scale, unidimensional) | D35: TRUE | E35: FALSE
A36: 7 | B36: Overall, I am satisfied with myself. | C36: Core Self-Evaluations (total scale, unidimensional) | D36: FALSE | E36: FALSE
A37: 8 | B37: I am filled with doubts about my competence. | C37: Core Self-Evaluations (total scale, unidimensional) | D37: TRUE | E37: FALSE
A38: 9 | B38: I determine what will happen in my life. | C38: Core Self-Evaluations (total scale, unidimensional) | D38: FALSE | E38: FALSE
A39: 10 | B39: I do not feel in control of my success in my career. | C39: Core Self-Evaluations (total scale, unidimensional) | D39: TRUE | E39: FALSE
A40: 11 | B40: I am capable of coping with most of my problems. | C40: Core Self-Evaluations (total scale, unidimensional) | D40: FALSE | E40: FALSE
A41: 12 | B41: There are times when things look pretty bleak and hopeless to me. | C41: Core Self-Evaluations (total scale, unidimensional) | D41: TRUE | E41: FALSE | F41: Touches on hopelessness; use sensitively with clients where wellbeing is a live concern.

Sheet PES Empowerment
A1: Psychological Empowerment Scale
A3: Instrument | B3: Psychological Empowerment Scale
A4: Code | B4: PES
A5: Domain | B5: 3. Adjacent occupational and wellbeing
A6: Availability | B6: Free / open access
A7: Construct | B7: Psychological empowerment at work, a motivational construct with four cognitive dimensions: meaning, competence, self-determination and impact.
A8: Respondent | B8: Self-report, employed adults
A9: Age range | B9: Working adults; original validation used middle managers and industrial-firm employees. Applicable to early-career and internship-stage clients holding a defined work role.
A10: Items in instrument | B10: 12
A11: Items reproduced here | B11: 12
A12: Administration time | B12: 3-5 minutes
A13: Cost and access | B13: The instrument is hosted freely by the developer, Gretchen Spreitzer, on her own university web page for research and practice use, with no stated fee or formal permission process.
A14: Coaching application | B14: This scale works well in coaching to make explicit which of the four empowerment dimensions (meaning, competence, self-determination, impact) is weakest for a client in a job, internship or leadership role, giving a concrete focus for goal-setting. It is designed for someone already in a defined work role with a 'department' or team, so it fits early-career and placement clients better than full-time students without paid work, and it measures a felt cognitive state rather than actual job conditions, so a low score should prompt exploration of both the client's perception and the realities of their role rather than being taken as a fixed trait.
... A27: Source URL | B27: https://webuser.bus.umich.edu/spreitze/Pdfs/EmpowerInstrument.pdf
A29: Item Number | B29: Item Text (verbatim) | C29: Subscale / Domain | D29: Reverse | E29: Filler | F29: Item Notes
A30: 1 | B30: The work that I do is important to me. | C30: Meaning | D30: FALSE | E30: FALSE
A31: 2 | B31: My job activities are personally meaningful to me. | C31: Meaning | D31: FALSE | E31: FALSE
A32: 3 | B32: The work I do is meaningful to me. | C32: Meaning | D32: FALSE | E32: FALSE
A33: 4 | B33: I am confident about my ability to do my job. | C33: Competence | D33: FALSE | E33: FALSE
A34: 5 | B34: I have mastered the skills necessary for my job. | C34: Competence | D34: FALSE | E34: FALSE
A35: 6 | B35: I am self-assured about my capabilities to perform my work activities. | C35: Competence | D35: FALSE | E35: FALSE
A36: 7 | B36: I have significant autonomy in determining how I do my job. | C36: Self-Determination | D36: FALSE | E36: FALSE
A37: 8 | B37: I can decide on my own how to go about doing my own work. | C37: Self-Determination | D37: FALSE | E37: FALSE
A38: 9 | B38: I have considerable opportunity for independence and freedom in how I do my job. | C38: Self-Determination | D38: FALSE | E38: FALSE
A39: 10 | B39: My impact on what happens in my department is large. | C39: Impact | D39: FALSE | E39: FALSE
A40: 11 | B40: I have a great deal of control over what happens in my department. | C40: Impact | D40: FALSE | E40: FALSE
A41: 12 | B41: I have significant influence over what happens in my department. | C41: Impact | D41: FALSE | E41: FALSE

Sheet DASS-21
A1: Depression Anxiety Stress Scales, 21 item version (DASS-21)
A3: Instrument | B3: Depression Anxiety Stress Scales, 21 item version (DASS-21)
A4: Code | B4: DASS-21
